Workbook

Sheet Tổng hợp
A1: Flow / Step ID | B1: Tên bước | C1: Áp dụng cho luồng | D1: Tổng TC | E1: Critical/Highest | F1: High | G1: Done | H1: % Done
A2: HF-01 | B2: Happy – E2E | C2: Kiểm tra luồng | D2: =COUNTIF(Mapping!$C$2:$C$750,A2) | E2: =COUNTIFS(Mapping!$C$2:$C$750,A2,Mapping!$O$2:$O$750,"Critical")+COUNTIFS(Mapping!$C$2:$C$750,A2,Mapping!$O$2:$O$750,"Highest") | F2: =COUNTIFS(Mapping!$C$2:$C$750,A2,Mapping!$O$2:$O$750,"High") | G2: =COUNTIFS(Mapping!$C$2:$C$750,A2,Mapping!$S$2:$S$750,"Done") | H2: =IF(D2=0,0,G2/D2)
A3: HF-02 | B3: Happy – E2E | C3: Kiểm tra luồng | D3: =COUNTIF(Mapping!$C$2:$C$750,A3) | E3: =COUNTIFS(Mapping!$C$2:$C$750,A3,Mapping!$O$2:$O$750,"Critical")+COUNTIFS(Mapping!$C$2:$C$750,A3,Mapping!$O$2:$O$750,"Highest") | F3: =COUNTIFS(Mapping!$C$2:$C$750,A3,Mapping!$O$2:$O$750,"High") | G3: =COUNTIFS(Mapping!$C$2:$C$750,A3,Mapping!$S$2:$S$750,"Done") | H3: =IF(D3=0,0,G3/D3)
A4: HF-03 | B4: Happy – E2E | C4: Kiểm tra luồng | D4: =COUNTIF(Mapping!$C$2:$C$750,A4) | E4: =COUNTIFS(Mapping!$C$2:$C$750,A4,Mapping!$O$2:$O$750,"Critical")+COUNTIFS(Mapping!$C$2:$C$750,A4,Mapping!$O$2:$O$750,"Highest") | F4: =COUNTIFS(Mapping!$C$2:$C$750,A4,Mapping!$O$2:$O$750,"High") | G4: =COUNTIFS(Mapping!$C$2:$C$750,A4,Mapping!$S$2:$S$750,"Done") | H4: =IF(D4=0,0,G4/D4)
A5: NE | B5: Negative – E2E | C5: Kiểm tra luồng | D5: =COUNTIF(Mapping!$C$2:$C$750,A5) | E5: =COUNTIFS(Mapping!$C$2:$C$750,A5,Mapping!$O$2:$O$750,"Critical")+COUNTIFS(Mapping!$C$2:$C$750,A5,Mapping!$O$2:$O$750,"Highest") | F5: =COUNTIFS(Mapping!$C$2:$C$750,A5,Mapping!$O$2:$O$750,"High") | G5: =COUNTIFS(Mapping!$C$2:$C$750,A5,Mapping!$S$2:$S$750,"Done") | H5: =IF(D5=0,0,G5/D5)
A6: S01 | B6: Danh sách & tìm kiếm giao dịch | C6: HF-01/02/03 | D6: =COUNTIF(Mapping!$C$2:$C$750,A6) | E6: =COUNTIFS(Mapping!$C$2:$C$750,A6,Mapping!$O$2:$O$750,"Critical")+COUNTIFS(Mapping!$C$2:$C$750,A6,Mapping!$O$2:$O$750,"Highest") | F6: =COUNTIFS(Mapping!$C$2:$C$750,A6,Mapping!$O$2:$O$750,"High") | G6: =COUNTIFS(Mapping!$C$2:$C$750,A6,Mapping!$S$2:$S$750,"Done") | H6: =IF(D6=0,0,G6/D6)
A7: S02 | B7: Thêm mới – quyền truy cập, điều hướng wizard, tích hợp CIF/GLIMS/Core, hạn mức ngày, Gửi duyệt/Lưu nháp | C7: HF-01/02/03 | D7: =COUNTIF(Mapping!$C$2:$C$750,A7) | E7: =COUNTIFS(Mapping!$C$2:$C$750,A7,Mapping!$O$2:$O$750,"Critical")+COUNTIFS(Mapping!$C$2:$C$750,A7,Mapping!$O$2:$O$750,"Highest") | F7: =COUNTIFS(Mapping!$C$2:$C$750,A7,Mapping!$O$2:$O$750,"High") | G7: =COUNTIFS(Mapping!$C$2:$C$750,A7,Mapping!$S$2:$S$750,"Done") | H7: =IF(D7=0,0,G7/D7)
A8: S03 | B8: Thêm mới – rule chung các trường (khoảng trắng, bắt buộc, độ dài, mặc định) | C8: HF-01/02/03 | D8: =COUNTIF(Mapping!$C$2:$C$750,A8) | E8: =COUNTIFS(Mapping!$C$2:$C$750,A8,Mapping!$O$2:$O$750,"Critical")+COUNTIFS(Mapping!$C$2:$C$750,A8,Mapping!$O$2:$O$750,"Highest") | F8: =COUNTIFS(Mapping!$C$2:$C$750,A8,Mapping!$O$2:$O$750,"High") | G8: =COUNTIFS(Mapping!$C$2:$C$750,A8,Mapping!$S$2:$S$750,"Done") | H8: =IF(D8=0,0,G8/D8)
A9: S04 | B9: Thêm mới – Thông tin khách hàng | C9: HF-01/02/03 | D9: =COUNTIF(Mapping!$C$2:$C$750,A9) | E9: =COUNTIFS(Mapping!$C$2:$C$750,A9,Mapping!$O$2:$O$750,"Critical")+COUNTIFS(Mapping!$C$2:$C$750,A9,Mapping!$O$2:$O$750,"Highest") | F9: =COUNTIFS(Mapping!$C$2:$C$750,A9,Mapping!$O$2:$O$750,"High") | G9: =COUNTIFS(Mapping!$C$2:$C$750,A9,Mapping!$S$2:$S$750,"Done") | H9: =IF(D9=0,0,G9/D9)
A10: S05 | B10: Thêm mới – Thông tin LC: loại LC, BIC, ngày, ngân hàng, bên phát hành, người hưởng | C10: HF-01/02/03 | D10: =COUNTIF(Mapping!$C$2:$C$750,A10) | E10: =COUNTIFS(Mapping!$C$2:$C$750,A10,Mapping!$O$2:$O$750,"Critical")+COUNTIFS(Mapping!$C$2:$C$750,A10,Mapping!$O$2:$O$750,"Highest") | F10: =COUNTIFS(Mapping!$C$2:$C$750,A10,Mapping!$O$2:$O$750,"High") | G10: =COUNTIFS(Mapping!$C$2:$C$750,A10,Mapping!$S$2:$S$750,"Done") | H10: =IF(D10=0,0,G10/D10)
A11: S06 | B11: Thêm mới – Giá trị LC, dung sai, nơi có giá trị | C11: HF-01/02/03 | D11: =COUNTIF(Mapping!$C$2:$C$750,A11) | E11: =COUNTIFS(Mapping!$C$2:$C$750,A11,Mapping!$O$2:$O$750,"Critical")+COUNTIFS(Mapping!$C$2:$C$750,A11,Mapping!$O$2:$O$750,"Highest") | F11: =COUNTIFS(Mapping!$C$2:$C$750,A11,Mapping!$O$2:$O$750,"High") | G11: =COUNTIFS(Mapping!$C$2:$C$750,A11,Mapping!$S$2:$S$750,"Done") | H11: =IF(D11=0,0,G11/D11)
A12: S07 | B12: Thêm mới – Phương thức thanh toán, hối phiếu, kỳ hạn | C12: HF-01/02/03 | D12: =COUNTIF(Mapping!$C$2:$C$750,A12) | E12: =COUNTIFS(Mapping!$C$2:$C$750,A12,Mapping!$O$2:$O$750,"Critical")+COUNTIFS(Mapping!$C$2:$C$750,A12,Mapping!$O$2:$O$750,"Highest") | F12: =COUNTIFS(Mapping!$C$2:$C$750,A12,Mapping!$O$2:$O$750,"High") | G12: =COUNTIFS(Mapping!$C$2:$C$750,A12,Mapping!$S$2:$S$750,"Done") | H12: =IF(D12=0,0,G12/D12)
A13: S08 | B13: Thêm mới – Giao hàng & hàng hoá | C13: HF-01/02/03 | D13: =COUNTIF(Mapping!$C$2:$C$750,A13) | E13: =COUNTIFS(Mapping!$C$2:$C$750,A13,Mapping!$O$2:$O$750,"Critical")+COUNTIFS(Mapping!$C$2:$C$750,A13,Mapping!$O$2:$O$750,"Highest") | F13: =COUNTIFS(Mapping!$C$2:$C$750,A13,Mapping!$O$2:$O$750,"High") | G13: =COUNTIFS(Mapping!$C$2:$C$750,A13,Mapping!$S$2:$S$750,"Done") | H13: =IF(D13=0,0,G13/D13)
... A33: P02 | B33: Dialog – Nhập thông tin hồ sơ hậu kiểm | C33: Sau phát hành (cần BO phát hành xong) | D33: =COUNTIF(Mapping!$C$2:$C$750,A33) | E33: =COUNTIFS(Mapping!$C$2:$C$750,A33,Mapping!$O$2:$O$750,"Critical")+COUNTIFS(Mapping!$C$2:$C$750,A33,Mapping!$O$2:$O$750,"Highest") | F33: =COUNTIFS(Mapping!$C$2:$C$750,A33,Mapping!$O$2:$O$750,"High") | G33: =COUNTIFS(Mapping!$C$2:$C$750,A33,Mapping!$S$2:$S$750,"Done") | H33: =IF(D33=0,0,G33/D33)
A34: TOTAL | D34: =SUM(D2:D33) | E34: =SUM(E2:E33) | F34: =SUM(F2:F33) | G34: =SUM(G2:G33) | H34: =IF(D34=0,0,G34/D34)

Sheet Mapping
A1: TC No | B1: Type | C1: Flow / Step ID | D1: Tên bước | E1: Áp dụng cho luồng | F1: Loại | G1: Màn hình (gốc) | H1: Function | I1: Điều kiện 1 | J1: Điều kiện 2 | K1: Summary | L1: Data | M1: Action | N1: Expected Result | O1: Priority | P1: Gợi ý automation | Q1: Automatable? | R1: Katalon Test Case | S1: Trạng thái | T1: Ghi chú | U1: Note (gốc)
A2: 1 | B2: FO-E2E | C2: HF-01 | D2: 1 cấp, không ký số PN | E2: Kiểm tra luồng | F2: Happy – E2E | G2: Tạo đề nghị phát hành | H2: Kiểm tra luồng | I2: Luồng happy case 1 cấp duyệt không ký số pháp nhân | K2: Kiểm tra luồng-Thành công-Tạo đề nghị phát hành-Luồng happy case 1 cấp duyệt không ký số pháp nhân-- | L2: 1 Marker 1 Kế toán trưởng 1 Chủ tài khoản | M2: Step: 1.User Maker login hệ thống FO. 2.Thêm mới 1 bản ghi phát hành LC, nhập liệu các trường thông tin bắt buộc (cấu hình 1 cấp duyệt 2FA, không ký số pháp nhân). 3.Maker thực hiện đẩy giao dịch lên cấp duyệt → bản ghi chuyển "Chờ duyệt". 4.User Kế toán trưởng login hệ thống FO, thực hiện xác thực 2FA và Phê duyệt. 5.User Chủ tài khoản login hệ thống FO, thực hiện Ký số thành công. 6.Quan sát kết quả. | N2: 1.Maker khởi tạo → Trạng thái: "Chờ duyệt". 2.Kế toán trưởng xác thực 2FA và duyệt xong → Trạng thái: "Chờ duyệt". 3.Chủ tài khoản ký số thành công → Hệ thống hiển thị màn hình thông báo thành công, bản ghi chuyển trạng thái "Đã gửi ngân hàng". | O2: Critical | P2: Cần xác nhận: 2FA/OTP; Cần xác nhận: ký số (USB token/HSM?) | S2: Not started
A3: 2 | B3: FO-E2E | C3: HF-01 | D3: 1 cấp, có ký số PN | E3: Kiểm tra luồng | F3: Happy – E2E | G3: Tạo đề nghị phát hành | H3: Kiểm tra luồng | I3: Luồng happy case 1 cấp duyệt có ký số pháp nhân | K3: Kiểm tra luồng-Thành công-Tạo đề nghị phát hành-Luồng happy case 1 cấp duyệt có ký số pháp nhân-- | L3: 1 Marker 1 Kế toán trưởng 1 Chủ tài khoản 1 Người ký pháp nhân | M3: Step: 1.User Maker login hệ thống FO. 2.Thêm mới 1 bản ghi phát hành LC, nhập liệu đầy đủ (cấu hình 1 cấp duyệt 2FA, có ký số pháp nhân). 3.Maker thực hiện đẩy giao dịch lên cấp duyệt → bản ghi chuyển "Chờ duyệt". 4.User Kế toán trưởng login hệ thống FO, thực hiện xác thực 2FA và Phê duyệt. 5.User Chủ tài khoản login hệ thống FO, thực hiện Ký số thành công → bản ghi chuyển trạng thái "Chờ ký số pháp nhân". 6.User đại diện pháp nhân login hệ thống FO, thực hiện Ký số pháp nhân thành công. 7.Quan sát kết quả. | N3: 1.Maker khởi tạo → Trạng thái: "Chờ duyệt". 2.Kế toán trưởng xác thực 2FA và duyệt xong → Trạng thái: "Chờ duyệt". 3.Chủ tài khoản ký số thành công → Trạng thái: "Chờ ký số pháp nhân". 4.Người đại diện pháp nhân ký số pháp nhân thành công → Hệ thống hiển thị màn hình thông báo thành công, bản ghi chuyển trạng thái "Đã gửi ngân hàng". | O3: Critical | P3: Cần xác nhận: 2FA/OTP; Cần xác nhận: ký số (USB token/HSM?) | S3: Not started
A4: 3 | B4: FO-E2E | C4: HF-01 | D4: 2 cấp, không ký số PN | E4: Kiểm tra luồng | F4: Happy – E2E | G4: Tạo đề nghị phát hành | H4: Kiểm tra luồng | I4: Luồng happy case 2 cấp duyệt không có ký số pháp nhân | K4: Kiểm tra luồng-Thành công-Tạo đề nghị phát hành-Luồng happy case 2 cấp duyệt không có ký số pháp nhân-- | L4: 1 Marker 1 Kế toán trưởng 1 Kế toán phó 1 Chủ tài khoản | M4: Step: 1.User Maker login hệ thống FO, thêm mới bản ghi phát hành LC, nhập liệu đầy đủ (cấu hình 2 cấp duyệt 2FA, không ký số pháp nhân). 2.Maker đẩy giao dịch lên cấp duyệt → bản ghi chuyển trạng thái "Chờ duyệt". 3.User Kế toán phó login, thực hiện xác thực 2FA và Phê duyệt → bản ghi chuyển trạng thái "Chờ duyệt cấp tiếp theo". 4.User Kế toán trưởng login, thực hiện xác thực 2FA và Phê duyệt. 5.User Chủ tài khoản login, thực hiện Ký số thành công. 6.Quan sát kết quả. | N4: 1.Maker khởi tạo → Trạng thái: "Chờ duyệt". 2.Kế toán phó xác thực 2FA và duyệt xong (2FA lần 1) → Trạng thái: "Chờ duyệt cấp tiếp theo". 3.Kế toán trưởng xác thực 2FA và duyệt xong (2FA lần 2) → Trạng thái: "Chờ duyệt cấp tiếp theo". 4.Chủ tài khoản ký số thành công → Hệ thống hiển thị màn hình thông báo thành công, bản ghi chuyển trạng thái "Đã gửi ngân hàng". | O4: Critical | P4: Cần xác nhận: 2FA/OTP; Cần xác nhận: ký số (USB token/HSM?) | S4: Not started
A5: 4 | B5: FO-E2E | C5: HF-01 | D5: 2 cấp, có ký số PN | E5: Kiểm tra luồng | F5: Happy – E2E | G5: Tạo đề nghị phát hành | H5: Kiểm tra luồng | I5: Luồng happy case 2 cấp duyệt có ký số pháp nhân | K5: Kiểm tra luồng-Thành công-Tạo đề nghị phát hành-Luồng happy case 2 cấp duyệt có ký số pháp nhân-- | L5: 1 Marker 1 Kế toán trưởng 1 Kế toán phó 1 Chủ tài khoản 1 Người ký pháp nhân | M5: Step: 1.User Maker login hệ thống FO, thêm mới bản ghi phát hành LC, nhập liệu đầy đủ (cấu hình 2 cấp duyệt 2FA, có ký số pháp nhân). 2.Maker đẩy giao dịch lên cấp duyệt → bản ghi chuyển trạng thái "Chờ duyệt". 3.User Kế toán phó login, thực hiện xác thực 2FA và Phê duyệt → bản ghi chuyển trạng thái "Chờ duyệt cấp tiếp theo". 4.User Kế toán trưởng login, thực hiện xác thực 2FA và Phê duyệt. 5.User Chủ tài khoản login, thực hiện Ký số thành công → bản ghi chuyển trạng thái "Chờ ký số pháp nhân". 6.Người dùng có thẩm quyền Ký số pháp nhân login, thực hiện ký số pháp nhân thành công. 7.Quan sát kết quả. | N5: 1.Maker khởi tạo → Trạng thái: "Chờ duyệt". 2.Kế toán phó xác thực 2FA và duyệt xong → Trạng thái: "Chờ duyệt cấp tiếp theo". 3.Kế toán trưởng xác thực 2FA và duyệt xong → Trạng thái: "Chờ duyệt cấp tiếp theo". 4.Chủ tài khoản ký số thành công → Trạng thái: "Chờ ký số pháp nhân". 5.Người đại diện pháp nhân ký số pháp nhân thành công → Hệ thống hiển thị màn hình thông báo thành công, bản ghi chuyển trạng thái "Đã gửi ngân hàng". | O5: Critical | P5: Cần xác nhận: 2FA/OTP; Cần xác nhận: ký số (USB token/HSM?) | S5: Not started
A6: 5 | B6: FO-E2E | C6: HF-02 | D6: 1 cấp, có ký số PN | E6: Kiểm tra luồng | F6: Happy – E2E | G6: Tạo đề nghị phát hành | H6: Kiểm tra luồng | I6: Luồng lưu nháp rồi phát hành 1 cấp duyệt có ký số pháp nhân | K6: Kiểm tra luồng-Thành công-Tạo đề nghị phát hành-Luồng lưu nháp rồi phát hành 1 cấp duyệt có ký số pháp nhân-- | L6: 1 Marker 1 Kế toán trưởng 1 Chủ tài khoản 1 Người ký pháp nhân | M6: Step: 1.User Maker login hệ thống FO, thêm mới bản ghi phát hành LC, nhập liệu đầy đủ. 2.Maker thực hiện <Lưu nháp>. 3.Maker mở lại bản ghi vừa lưu nháp, đẩy giao dịch lên cấp duyệt → bản ghi chuyển "Chờ duyệt". 4.User Kế toán trưởng login, thực hiện xác thực 2FA và Phê duyệt. 5.User Chủ tài khoản login, thực hiện Ký số thành công. 6.Người dùng có thẩm quyền Ký số pháp nhân login, thực hiện ký số pháp nhân thành công. 7.Quan sát kết quả. | N6: 1.Maker khởi tạo → Trạng thái: "Khởi tạo phát hành". 2.Maker lưu nháp → Trạng thái: "Bản nháp". 3.Maker đẩy giao dịch lên cấp duyệt → Trạng thái: "Chờ duyệt". 4.Kế toán trưởng xác thực 2FA và duyệt xong → Trạng thái: "Chờ duyệt". 5.Chủ tài khoản ký số thành công → Trạng thái: "Chờ ký số pháp nhân". 6.Người đại diện pháp nhân ký số pháp nhân thành công → Hệ thống hiển thị màn hình thông báo thành công, bản ghi chuyển trạng thái "Đã gửi ngân hàng". | O6: High | P6: Cần xác nhận: 2FA/OTP; Cần xác nhận: ký số (USB token/HSM?) | S6: Not started
A7: 6 | B7: FO-E2E | C7: HF-02 | D7: 2 cấp, có ký số PN | E7: Kiểm tra luồng | F7: Happy – E2E | G7: Tạo đề nghị phát hành | H7: Kiểm tra luồng | I7: Luồng lưu nháp rồi phát hành 2 cấp duyệt có ký số pháp nhân | K7: Kiểm tra luồng-Thành công-Tạo đề nghị phát hành-Luồng lưu nháp rồi phát hành 1 cấp duyệt có ký số pháp nhân-- | L7: 1 Marker 1 Kế toán trưởng 1 Kế toán phó 1 Chủ tài khoản 1 Người ký pháp nhân | M7: Step: 1.User Maker login hệ thống FO, thêm mới bản ghi phát hành LC, nhập liệu đầy đủ. 2.Maker thực hiện <Lưu nháp>. 3.Maker mở lại bản ghi vừa lưu nháp, đẩy giao dịch lên cấp duyệt → "Chờ duyệt". 4.User Kế toán phó login, xác thực 2FA và Phê duyệt → bản ghi chuyển "Chờ duyệt cấp tiếp theo". 5.User Kế toán trưởng login, xác thực 2FA và Phê duyệt. 6.User Chủ tài khoản login, thực hiện Ký số thành công → "Chờ ký số pháp nhân". 7.Người dùng có thẩm quyền Ký số pháp nhân thực hiện ký số pháp nhân thành công. 8.Quan sát kết quả. | N7: 1.Maker khởi tạo → Trạng thái: "Khởi tạo phát hành". 2.Maker lưu nháp → Trạng thái: "Bản nháp". 3.Maker đẩy giao dịch lên cấp duyệt → Trạng thái: "Chờ duyệt". 4.Kế toán phó xác thực 2FA và duyệt xong → Trạng thái: "Chờ duyệt cấp tiếp theo". 5.Kế toán trưởng xác thực 2FA và duyệt xong → Trạng thái: "Chờ duyệt cấp tiếp theo". 6.Chủ tài khoản ký số thành công → Trạng thái: "Chờ ký số pháp nhân". 7.Người đại diện pháp nhân ký số pháp nhân thành công → Hệ thống hiển thị màn hình thông báo thành công, bản ghi chuyển trạng thái "Đã gửi ngân hàng". | O7: High | P7: Cần xác nhận: 2FA/OTP; Cần xác nhận: ký số (USB token/HSM?) | S7: Not started
A8: 7 | B8: FO-E2E | C8: HF-02 | D8: 1 cấp, không ký số PN | E8: Kiểm tra luồng | F8: Happy – E2E | G8: Tạo đề nghị phát hành | H8: Kiểm tra luồng | I8: Luồng lưu nháp rồi phát hành 1 cấp duyệt không có ký số pháp nhân | K8: Kiểm tra luồng-Thành công-Tạo đề nghị phát hành-Luồng lưu nháp rồi phát hành 1 cấp duyệt không có ký số pháp nhân-- | L8: 1 Marker 1 Kế toán trưởng 1 Chủ tài khoản | M8: Step: 1.User Maker login hệ thống FO, thêm mới bản ghi phát hành LC, nhập liệu đầy đủ. 2.Maker thực hiện <Lưu nháp>. 3.Maker mở lại bản ghi vừa lưu nháp, đẩy giao dịch lên cấp duyệt → bản ghi chuyển "Chờ duyệt". 4.User Kế toán trưởng login, thực hiện xác thực 2FA và Phê duyệt. 5.User Chủ tài khoản login, thực hiện Ký số thành công. 6.Quan sát kết quả. | N8: 1.Maker khởi tạo → Trạng thái: "Khởi tạo phát hành". 2.Maker lưu nháp → Trạng thái: "Bản nháp". 3.Maker đẩy giao dịch lên cấp duyệt → Trạng thái: "Chờ duyệt". 4.Kế toán trưởng xác thực 2FA và duyệt xong → Trạng thái: "Chờ duyệt". 5.Chủ tài khoản ký số thành công → Hệ thống hiển thị màn hình thông báo thành công, bản ghi chuyển trạng thái "Đã gửi ngân hàng". | O8: High | P8: Cần xác nhận: 2FA/OTP; Cần xác nhận: ký số (USB token/HSM?) | S8: Not started
A9: 8 | B9: FO-E2E | C9: HF-02 | D9: 2 cấp, không ký số PN | E9: Kiểm tra luồng | F9: Happy – E2E | G9: Tạo đề nghị phát hành | H9: Kiểm tra luồng | I9: Luồng lưu nháp rồi phát hành 2 cấp duyệt không có ký số pháp nhân | K9: Kiểm tra luồng-Thành công-Tạo đề nghị phát hành-Luồng lưu nháp rồi phát hành 2 cấp duyệt không có ký số pháp nhân-- | L9: 1 Marker 1 Kế toán trưởng 1 Kế toán phó 1 Chủ tài khoản | M9: Step: 1.User Maker login hệ thống FO, thêm mới bản ghi phát hành LC, nhập liệu đầy đủ. 2.Maker thực hiện <Lưu nháp>. 3.Maker mở lại bản ghi vừa lưu nháp, đẩy giao dịch lên cấp duyệt → bản ghi chuyển "Chờ duyệt". 4.User Kế toán phó login, thực hiện xác thực 2FA và Phê duyệt → bản ghi chuyển "Chờ duyệt cấp tiếp theo". 5.User Kế toán trưởng login, thực hiện xác thực 2FA và Phê duyệt. 6.User Chủ tài khoản login, thực hiện Ký số thành công. 7.Quan sát kết quả. | N9: 1.Maker khởi tạo → Trạng thái: "Khởi tạo phát hành". 2.Maker lưu nháp → Trạng thái: "Bản nháp". 3.Maker đẩy giao dịch lên cấp duyệt → Trạng thái: "Chờ duyệt". 4.Kế toán phó xác thực 2FA và duyệt xong → Trạng thái: "Chờ duyệt cấp tiếp theo". 5.Kế toán trưởng xác thực 2FA và duyệt xong → Trạng thái: "Chờ duyệt cấp tiếp theo". 6.Chủ tài khoản ký số thành công → Hệ thống hiển thị màn hình thông báo thành công, bản ghi chuyển trạng thái "Đã gửi ngân hàng". | O9: High | P9: Cần xác nhận: 2FA/OTP; Cần xác nhận: ký số (USB token/HSM?) | S9: Not started
A10: 9 | B10: FO-E2E | C10: NE | D10: Hủy giao dịch từ bản nháp → Đã hủy | E10: Kiểm tra luồng | F10: Negative – E2E | G10: Tạo đề nghị phát hành | H10: Kiểm tra luồng | I10: Hủy giao dịch từ bản nháp | K10: Kiểm tra luồng-Thành công-Tạo đề nghị phát hành-Luồng lưu nháp rồi phát hành 2 cấp duyệt có ký số pháp nhân-- | L10: 1 Marker | M10: Step: 1.User Maker login hệ thống FO, thêm mới bản ghi phát hành LC, nhập liệu đầy đủ. 2.Maker thực hiện <Lưu nháp>. 3.Maker mở lại bản ghi, chọn chức năng <Hủy đề nghị>, xác nhận hủy. 4.Quan sát kết quả. | N10: 1.Maker khởi tạo → Trạng thái: "Khởi tạo phát hành". 2.Maker lưu nháp → Trạng thái: "Bản nháp". 3.Maker thực hiện hủy đề nghị → Trạng thái: "Đã hủy". | O10: High | P10: Cần xác nhận: ký số (USB token/HSM?) | S10: Not started
A11: 10 | B11: FO-E2E | C11: NE | D11: Từ chối tại Kế toán trưởng → Đã hủy | E11: Kiểm tra luồng | F11: Negative – E2E | G11: Tạo đề nghị phát hành | H11: Kiểm tra luồng | I11: Từ chối tại Kế toán trưởng | K11: Kiểm tra luồng-Thành công-Tạo đề nghị phát hành-Luồng lưu nháp rồi phát hành 1 cấp duyệt không có ký số pháp nhân-- | L11: 1 Marker 1 Checker | M11: Step: 1.User Maker login hệ thống FO, thêm mới bản ghi phát hành LC, nhập liệu đầy đủ, đẩy giao dịch lên cấp duyệt → bản ghi chuyển "Chờ duyệt". 2.User Kế toán trưởng (Checker) login, truy cập bản ghi, chọn <Từ chối>, nhập lý do, xác nhận. 3.Quan sát kết quả. | N11: 1.Maker khởi tạo → Trạng thái: "Chờ duyệt". 2.Kế toán trưởng từ chối bản ghi → Trạng thái: "Đã hủy". | O11: Critical | P11: Cần xác nhận: ký số (USB token/HSM?) | S11: Not started
A12: 11 | B12: FO-E2E | C12: NE | D12: Từ chối tại Chủ tài khoản → Từ chối | E12: Kiểm tra luồng | F12: Negative – E2E | G12: Tạo đề nghị phát hành | H12: Kiểm tra luồng | I12: Từ chối tại Chủ tài khoản | K12: Kiểm tra luồng-từ chối giao dịch-Tạo đề nghị phát hành-Từ chối tại Chủ tài khoản-- | L12: 1 Marker 1 Kế toán trưởng 1 Chủ tài khoản | M12: Step: 1.User Maker login hệ thống FO, thêm mới bản ghi phát hành LC, nhập liệu đầy đủ, đẩy giao dịch lên cấp duyệt → "Chờ duyệt". 2.User Kế toán trưởng login, thực hiện xác thực 2FA và Phê duyệt giao dịch → bản ghi chuyển "Chờ duyệt cấp tiếp theo". 3.User Chủ tài khoản login, chọn <Từ chối> bản ghi, nhập lý do, xác nhận. 4.Quan sát kết quả. | N12: 1.Maker khởi tạo → Trạng thái: "Chờ duyệt". 2.Kế toán trưởng xác thực 2FA và duyệt xong → Trạng thái: "Chờ duyệt cấp tiếp theo". 3.Chủ tài khoản từ chối bản ghi → Trạng thái: "Từ chối". | O12: Critical | P12: Cần xác nhận: 2FA/OTP | S12: Not started
A13: 12 | B13: FO-E2E | C13: NE | D13: Bước Ký số pháp nhân KHÔNG có nút Từ chối | E13: Kiểm tra luồng | F13: Negative – E2E | G13: Tạo đề nghị phát hành | H13: Kiểm tra luồng | I13: Kiểm tra bước Ký số pháp nhân KHÔNG có tùy chọn Từ chối | K13: Kiểm tra luồng-Thành công-Tạo đề nghị phát hành-Kiểm tra bước Ký số pháp nhân KHÔNG có tùy chọn Từ chối-- | L13: 1 Marker 1 Kế toán trưởng 1 Chủ tài khoản 1 Người ký pháp nhân | M13: Step: 1.User Maker login hệ thống FO, thêm mới bản ghi phát hành LC, nhập liệu đầy đủ, đẩy giao dịch lên cấp duyệt. 2.User Kế toán trưởng login, thực hiện xác thực 2FA và Phê duyệt. 3.User Chủ tài khoản login, thực hiện Ký số thành công → bản ghi chuyển "Chờ ký số pháp nhân". 4.Người dùng có thẩm quyền Ký số pháp nhân login, mở màn hình xử lý bản ghi. 5.Quan sát các nút chức năng hiển thị trên màn hình. | N13: Tại bước "Chờ ký số pháp nhân", màn hình KHÔNG hiển thị nút <Từ chối> — người dùng có thẩm quyền Ký số pháp nhân chỉ có thể thực hiện Ký số pháp nhân (đồng ý) để hoàn tất giao dịch, không có quyền từ chối giao dịch tại bước này. | O13: Medium | P13: Cần xác nhận: 2FA/OTP; Cần xác nhận: ký số (USB token/HSM?) | S13: Not started
A14: 13 | B14: FO-E2E | C14: NE | D14: Trả lại → Maker hủy → Đã hủy | E14: Kiểm tra luồng | F14: Negative – E2E | G14: Tạo đề nghị phát hành | H14: Kiểm tra luồng | I14: Yêu cầu chỉnh sửa rồi hủy | K14: Kiểm tra luồng-Huỷ giao dịch-Tạo đề nghị phát hành-Hủy giao dịch từ bản nháp-- | L14: 1 Marker 1 Checker | M14: Step: 1.User Maker login hệ thống FO, thêm mới bản ghi phát hành LC, nhập liệu đầy đủ, đẩy giao dịch lên cấp duyệt → "Chờ duyệt". 2.User Kế toán trưởng (Checker) login, truy cập bản ghi, chọn <Trả lại>, nhập ý kiến, xác nhận. 3.User Maker mở lại giao dịch (nay ở trạng thái "Yêu cầu chỉnh sửa"), chọn chức năng <Hủy đề nghị>, xác nhận hủy. 4.Quan sát kết quả. | N14: 1.Maker khởi tạo → Trạng thái: "Chờ duyệt". 2.Kế toán trưởng trả lại bản ghi → Trạng thái: "Yêu cầu chỉnh sửa". 3.Maker thực hiện hủy giao dịch → Trạng thái: "Đã hủy". | O14: High | S14: Not started
A15: 14 | B15: FO-E2E | C15: HF-03 | D15: 1 cấp, không ký số PN | E15: Kiểm tra luồng | F15: Happy – E2E | G15: Tạo đề nghị phát hành | H15: Kiểm tra luồng | I15: Yêu cầu chỉnh sửa rồi phát hành thành công luồng duyệt 1 cấp không ký số pháp nhân | K15: Kiểm tra luồng-từ chối giao dịch-Tạo đề nghị phát hành-Từ chối tại Kế toán trưởng-- | L15: 1 Marker 1 Kế toán trưởng 1 Chủ tài khoản | M15: Step: 1.User Maker login hệ thống FO, thêm mới bản ghi phát hành LC, nhập liệu đầy đủ, đẩy giao dịch lên cấp duyệt → "Chờ duyệt". 2.User Kế toán trưởng login, chọn <Trả lại>, nhập ý kiến, xác nhận → bản ghi chuyển "Yêu cầu chỉnh sửa". 3.User Maker mở lại giao dịch, chỉnh sửa thông tin theo ý kiến, gửi lại bản ghi → bản ghi chuyển "Chờ duyệt". 4.User Kế toán trưởng thực hiện xác thực 2FA và Phê duyệt. 5.User Chủ tài khoản thực hiện Ký số thành công. 6.Quan sát kết quả. | N15: 1.Maker khởi tạo → Trạng thái: "Chờ duyệt". 2.Kế toán trưởng thực hiện Trả lại → Trạng thái: "Yêu cầu chỉnh sửa". 3.Maker chỉnh sửa và gửi lại bản ghi → Trạng thái: "Chờ duyệt". 4.Kế toán trưởng xác thực 2FA và duyệt xong → Trạng thái: "Chờ duyệt". 5.Chủ tài khoản ký số thành công → Hệ thống hiển thị màn hình thông báo thành công, bản ghi chuyển trạng thái "Đã gửi ngân hàng". | O15: Critical | P15: Cần xác nhận: 2FA/OTP; Cần xác nhận: ký số (USB token/HSM?) | S15: Not started
A16: 15 | B16: FO-E2E | C16: HF-03 | D16: 1 cấp, có ký số PN | E16: Kiểm tra luồng | F16: Happy – E2E | G16: Tạo đề nghị phát hành | H16: Kiểm tra luồng | I16: Yêu cầu chỉnh sửa rồi phát hành thành công luồng duyệt 1 cấp có ký số pháp nhân | K16: Kiểm tra luồng-từ chối giao dịch-Tạo đề nghị phát hành-Từ chối tại Chủ tài khoản-- | L16: 1 Marker 1 Kế toán trưởng 1 Chủ tài khoản 1 Người ký pháp nhân | M16: Step: 1.User Maker login hệ thống FO, thêm mới bản ghi phát hành LC, nhập liệu đầy đủ, đẩy giao dịch lên cấp duyệt → "Chờ duyệt". 2.User Kế toán trưởng login, chọn <Trả lại>, nhập ý kiến, xác nhận → bản ghi chuyển "Yêu cầu chỉnh sửa". 3.User Maker chỉnh sửa thông tin, gửi lại bản ghi → "Chờ duyệt". 4.User Kế toán trưởng thực hiện xác thực 2FA và Phê duyệt. 5.User Chủ tài khoản thực hiện Ký số thành công → "Chờ ký số pháp nhân". 6.Người đại diện pháp nhân thực hiện ký số pháp nhân thành công. 7.Quan sát kết quả. | N16: 1.Maker khởi tạo → Trạng thái: "Chờ duyệt". 2.Kế toán trưởng thực hiện Trả lại → Trạng thái: "Yêu cầu chỉnh sửa". 3.Maker chỉnh sửa và gửi lại bản ghi → Trạng thái: "Chờ duyệt". 4.Kế toán trưởng xác thực 2FA và duyệt xong → Trạng thái: "Chờ duyệt". 5.Chủ tài khoản ký số thành công → Trạng thái: "Chờ ký số pháp nhân". 6.Người đại diện pháp nhân ký số pháp nhân thành công → Hệ thống hiển thị màn hình thông báo thành công, bản ghi chuyển trạng thái "Đã gửi ngân hàng". | O16: Critical | P16: Cần xác nhận: 2FA/OTP; Cần xác nhận: ký số (USB token/HSM?) | S16: Not started
A17: 16 | B17: FO-E2E | C17: HF-03 | D17: 2 cấp, không ký số PN | E17: Kiểm tra luồng | F17: Happy – E2E | G17: Tạo đề nghị phát hành | H17: Kiểm tra luồng | I17: Yêu cầu chỉnh sửa rồi phát hành thành công luồng duyệt 2 cấp không ký số pháp nhân | K17: Kiểm tra luồng-Thành công-Tạo đề nghị phát hành-Kiểm tra bước Ký số pháp nhân KHÔNG có tùy chọn Từ chối-- | L17: 1 Marker 1 Kế toán trưởng 1 Kế toán phó 1 Chủ tài khoản | M17: Step: 1.User Maker login hệ thống FO, thêm mới bản ghi phát hành LC, nhập liệu đầy đủ, đẩy giao dịch lên cấp duyệt → "Chờ duyệt". 2.User Kế toán phó login, chọn <Trả lại>, nhập ý kiến, xác nhận → bản ghi chuyển "Yêu cầu chỉnh sửa". 3.User Maker chỉnh sửa thông tin, gửi lại bản ghi → "Chờ duyệt". 4.User Kế toán phó thực hiện xác thực 2FA và Phê duyệt → bản ghi chuyển "Chờ duyệt cấp tiếp theo". 5.User Kế toán trưởng thực hiện xác thực 2FA và Phê duyệt. 6.User Chủ tài khoản thực hiện Ký số thành công. 7.Quan sát kết quả. | N17: 1.Maker khởi tạo → Trạng thái: "Chờ duyệt". 2.Kế toán phó thực hiện Trả lại → Trạng thái: "Yêu cầu chỉnh sửa". 3.Maker chỉnh sửa và gửi lại bản ghi → Trạng thái: "Chờ duyệt". 4.Kế toán phó xác thực 2FA và duyệt xong → Trạng thái: "Chờ duyệt cấp tiếp theo". 5.Kế toán trưởng xác thực 2FA và duyệt xong → Trạng thái: "Chờ duyệt cấp tiếp theo". 6.Chủ tài khoản ký số thành công → Hệ thống hiển thị màn hình thông báo thành công, bản ghi chuyển trạng thái "Đã gửi ngân hàng". | O17: Critical | P17: Cần xác nhận: 2FA/OTP; Cần xác nhận: ký số (USB token/HSM?) | S17: Not started
A18: 17 | B18: FO-E2E | C18: HF-03 | D18: 2 cấp, có ký số PN | E18: Kiểm tra luồng | F18: Happy – E2E | G18: Tạo đề nghị phát hành | H18: Kiểm tra luồng | I18: Yêu cầu chỉnh sửa rồi phát hành thành công luồng duyệt 2 cấp có ký số pháp nhân | K18: Kiểm tra luồng-Huỷ giao dịch-Tạo đề nghị phát hành-Yêu cầu chỉnh sửa rồi hủy-- | L18: 1 Marker 1 Kế toán trưởng 1 Kế toán phó 1 Chủ tài khoản 1 Người ký pháp nhân | M18: Step: 1.User Maker login hệ thống FO, thêm mới bản ghi phát hành LC, nhập liệu đầy đủ, đẩy giao dịch lên cấp duyệt → "Chờ duyệt". 2.User Kế toán phó login, chọn <Trả lại>, nhập ý kiến, xác nhận → bản ghi chuyển "Yêu cầu chỉnh sửa". 3.User Maker chỉnh sửa thông tin, gửi lại bản ghi → "Chờ duyệt". 4.User Kế toán phó thực hiện xác thực 2FA và Phê duyệt → bản ghi chuyển "Chờ duyệt cấp tiếp theo". 5.User Kế toán trưởng thực hiện xác thực 2FA và Phê duyệt. 6.User Chủ tài khoản thực hiện Ký số thành công → "Chờ ký số pháp nhân". 7.Người đại diện pháp nhân thực hiện Ký số pháp nhân thành công. 8.Quan sát kết quả. | N18: 1.Maker khởi tạo → Trạng thái: "Chờ duyệt". 2.Kế toán phó thực hiện Trả lại → Trạng thái: "Yêu cầu chỉnh sửa". 3.Maker chỉnh sửa và gửi lại bản ghi → Trạng thái: "Chờ duyệt". 4.Kế toán phó xác thực 2FA và duyệt xong → Trạng thái: "Chờ duyệt cấp tiếp theo". 5.Kế toán trưởng xác thực 2FA và duyệt xong → Trạng thái: "Chờ duyệt cấp tiếp theo". 6.Chủ tài khoản ký số thành công → Trạng thái: "Chờ ký số pháp nhân". 7.Người đại diện pháp nhân ký số pháp nhân thành công → Hệ thống hiển thị màn hình thông báo thành công, bản ghi chuyển trạng thái "Đã gửi ngân hàng". | O18: Critical | P18: Cần xác nhận: 2FA/OTP; Cần xác nhận: ký số (USB token/HSM?) | S18: Not started
A19: 66 | B19: FO | C19: S01 | D19: Danh sách & tìm kiếm giao dịch | E19: HF-01/02/03 | F19: Edge case | G19: Danh sách và tìm kiếm giao dịch | H19: Kiểm tra quyền truy cập chức năng "Danh sách và tìm kiếm giao dịch" (FO) | I19: Kiểm tra quyền truy cập chức năng "Danh sách và tìm kiếm giao dịch" (FO) | K19: Kiểm tra luồng-Thất bại-BO - Luồng xử lý giao dịch Phát hành LC-Luồng (2) – Đề xuất từ chối - Không cần thẩm quyền BGĐ CN-CA lead phê duyệt (2), không thuộc thẩm quyền BGĐ CN → CA từ chối-LC không được phát hành | L19: 1 Marker | M19: Pre: - Tồn tại 1 hồ sơ đề nghị Phát hành LC có trạng thái khác Bản nháp Step: 1. Đăng nhập hệ thống bằng user có quyền xem chi tiết. 2. Mở màn hình xem chi tiết hồ sơ có trạng thái khác Bản nháp. 3. Quan sát khu vực các nút chức năng trên màn hình. | N19: Nút <Xóa đề nghị> không hiển thị trên màn hình (do BR quy định nút chỉ hiển thị với TT = Bản nháp). | O19: Medium | S19: Not started
A20: 67 | B20: FO | C20: S01 | D20: Danh sách & tìm kiếm giao dịch | E20: HF-01/02/03 | F20: Edge case | G20: Danh sách và tìm kiếm giao dịch | H20: Kiểm tra chặn truy cập chức năng "Danh sách và tìm kiếm giao dịch" (FO) khi không được phân quyền | I20: Kiểm tra chặn truy cập chức năng "Danh sách và tìm kiếm giao dịch" (FO) khi không được phân quyền | K20: Kiểm tra luồng-Thất bại-BO - Luồng xử lý giao dịch Phát hành LC-Luồng (2) – Đề xuất từ chối - Không cần thẩm quyền BGĐ CN-CRC lead phê duyệt (2), không thuộc thẩm quyền BGĐ CN → CA từ chối-LC không được phát hành | L20: 1 Marker | M20: Step: Đăng nhập hệ thống với user KHÔNG được phân quyền chức năng "Danh sách và tìm kiếm giao dịch", thử truy cập chức năng. | N20: User không nhìn thấy/không truy cập được chức năng "Danh sách và tìm kiếm giao dịch" trên giao diện. | O20: High | S20: Not started
A21: 68 | B21: FO | C21: S01 | D21: Danh sách & tìm kiếm giao dịch | E21: HF-01/02/03 | F21: Edge case | G21: Danh sách và tìm kiếm giao dịch | H21: Kiểm tra hệ thống gọi API tới BO Admin Portal để lấy thông tin phân quyền (CIF, cây phân quyền, roleName) ngay sau khi đăng nhập thành công | I21: Kiểm tra hệ thống gọi API tới BO Admin Portal để lấy thông tin phân quyền (CIF, cây phân quyền, roleName) ngay sau khi đăng nhập thành công | K21: Kiểm tra luồng-Thất bại-BO - Luồng xử lý giao dịch Phát hành LC-Luồng (2) – Đề xuất từ chối - Không cần thẩm quyền BGĐ CN-CA lead phê duyệt (2), không thuộc thẩm quyền BGĐ CN → quay lại CA, CA trả lại Doanh nghiệp → Doanh nghiệp hủy đề nghị-LC không được phát hành | L21: 1 Marker | M21: Pre: - NSD đã có tài khoản được cấp quyền truy vấn giao dịch (cây phân quyền TTTM > LCNK > Phát hành LC (PHLC) > Truy vấn hồ sơ (V_PHLC)) trên BO Admin Portal Step: 1. NSD đăng nhập thành công vào hệ thống. 2. NSD truy cập theo đường dẫn: Phát hành LC. 3. Quan sát màn hình Danh sách và tìm kiếm giao dịch phát hành LC. | N21: Hệ thống đã gọi API tới hệ thống BO Admin Portal để lấy thông tin CIF của user, cây phân quyền (Permission) và roleName theo đúng cây phân quyền 4 tầng: TTTM (Tài trợ thương mại) > LCNK (LC nhập khẩu) > Phát hành LC (Mã PHLC) > Truy vấn hồ sơ (Mã V_PHLC). Màn hình danh sách giao dịch phát hành LC hiển thị thành công cho NSD. | O21: High | P21: Cần xác nhận: gọi API ngoài | S21: Not started
A22: 69 | B22: FO | C22: S01 | D22: Danh sách & tìm kiếm giao dịch | E22: HF-01/02/03 | F22: Edge case | G22: Danh sách và tìm kiếm giao dịch | H22: Kiểm tra hậu điều kiện phân quyền theo CIF: NSD chỉ xem được toàn bộ danh sách giao dịch đề nghị phát hành LC thuộc chính CIF của mình | I22: Kiểm tra hậu điều kiện phân quyền theo CIF: NSD chỉ xem được toàn bộ danh sách giao dịch đề nghị phát hành LC thuộc chính CIF của mình | K22: Kiểm tra luồng-Thất bại-BO - Luồng xử lý giao dịch Phát hành LC-Luồng (2) – Đề xuất từ chối - Không cần thẩm quyền BGĐ CN-CRC lead phê duyệt (2), không thuộc thẩm quyền BGĐ CN → quay lại CA, CA trả lại Doanh nghiệp → Doanh nghiệp hủy đề nghị-LC không được phát hành | L22: 1 Marker | M22: Pre: - NSD đã đăng nhập thành công và được phân quyền truy vấn giao dịch (mã V_PHLC) trên CIF của DN đang login; hệ thống đang có giao dịch phát hành LC của nhiều CIF khác nhau Step: 1. NSD đăng nhập vào hệ thống với tài khoản thuộc CIF A. 2. NSD truy cập đường dẫn Phát hành LC. 3. Quan sát danh sách giao dịch hiển thị trên màn hình. | N22: Hệ thống chỉ hiển thị toàn bộ danh sách giao dịch đề nghị phát hành LC thuộc CIF A (CIF của user đang truy cập), không hiển thị giao dịch của CIF khác, đúng theo hậu điều kiện: "Xem được toàn bộ danh sách giao dịch của chính user truy cập". | O22: High | S22: Not started
A23: 70 | B23: FO | C23: S01 | D23: Danh sách & tìm kiếm giao dịch | E23: HF-01/02/03 | F23: Edge case | G23: Danh sách và tìm kiếm giao dịch | H23: Kiểm tra chức năng tìm kiếm nhanh (realtime) trên khung tìm kiếm theo trường Mã đề nghị | I23: Kiểm tra chức năng tìm kiếm nhanh (realtime) trên khung tìm kiếm theo trường Mã đề nghị | K23: Kiểm tra quyền truy cập chức năng "Danh sách và tìm kiếm giao dịch" (FO)-Thành công-Danh sách và tìm kiếm giao dịch-Kiểm tra quyền truy cập chức năng "Danh sách và tìm kiếm giao dịch" (FO)-- | L23: 1 Marker | M23: Pre: - NSD đã đăng nhập và đang ở màn hình danh sách giao dịch phát hành LC, có sẵn dữ liệu giao dịch Step: 1. Tại khung tìm kiếm, NSD nhập giá trị hợp lệ (một phần hoặc toàn bộ) vào trường [Mã đề nghị]. 2. Quan sát danh sách kết quả mà không cần nhấn thêm nút tìm kiếm nào khác. | N23: Hệ thống trả kết quả hiển thị realtime trên danh sách, chỉ hiển thị các giao dịch có Mã đề nghị chứa (CONTAIN) giá trị NSD vừa nhập. | O23: High | S23: Not started
A24: 71 | B24: FO | C24: S01 | D24: Danh sách & tìm kiếm giao dịch | E24: HF-01/02/03 | F24: Edge case | G24: Danh sách và tìm kiếm giao dịch | H24: Kiểm tra chức năng tìm kiếm nhanh (realtime) trên khung tìm kiếm theo trường Bên nhận LC | I24: Kiểm tra chức năng tìm kiếm nhanh (realtime) trên khung tìm kiếm theo trường Bên nhận LC | K24: Kiểm tra chặn truy cập chức năng "Danh sách và tìm kiếm giao dịch" (FO) khi không được phân quyền-Thành công-Danh sách và tìm kiếm giao dịch-Kiểm tra chặn truy cập chức năng "Danh sách và tìm kiếm giao dịch" (FO) khi không được phân quyền-- | L24: 1 Marker | M24: Pre: - NSD đã đăng nhập và đang ở màn hình danh sách giao dịch phát hành LC, có sẵn dữ liệu giao dịch Step: 1. Tại khung tìm kiếm, NSD nhập giá trị hợp lệ vào trường [Bên nhận LC]. 2. Quan sát danh sách kết quả. | N24: Hệ thống trả kết quả hiển thị realtime trên danh sách, chỉ hiển thị các giao dịch có Bên nhận LC chứa (CONTAIN) giá trị NSD vừa nhập. | O24: Medium | S24: Not started
A25: 72 | B25: FO | C25: S01 | D25: Danh sách & tìm kiếm giao dịch | E25: HF-01/02/03 | F25: Edge case | G25: Danh sách và tìm kiếm giao dịch | H25: Kiểm tra chức năng tìm kiếm nhanh (realtime) trên khung tìm kiếm theo trường Số tiền | I25: Kiểm tra chức năng tìm kiếm nhanh (realtime) trên khung tìm kiếm theo trường Số tiền | K25: Kiểm tra hệ thống gọi API tới BO Admin Portal để lấy thông tin phân quyền (CIF, cây phân quyền, roleName) ngay sau khi đăng nhập thành công-Thành công-Danh sách và tìm kiếm giao dịch-Kiểm tra hệ thống gọi API tới BO Admin Portal để lấy thông tin phân quyền (CIF, cây phân quyền, roleName) ngay sau khi đăng nhập thành công-- | L25: 1 Marker | M25: Pre: - NSD đã đăng nhập và đang ở màn hình danh sách giao dịch phát hành LC, có sẵn dữ liệu giao dịch Step: 1. Tại khung tìm kiếm, NSD nhập giá trị vào trường [Số tiền]. 2. Quan sát danh sách kết quả. | N25: Hệ thống trả kết quả hiển thị realtime trên danh sách, chỉ hiển thị các giao dịch có Số tiền chứa (CONTAIN) giá trị NSD vừa nhập. | O25: Medium | P25: Cần xác nhận: gọi API ngoài | S25: Not started
A26: 73 | B26: FO | C26: S01 | D26: Danh sách & tìm kiếm giao dịch | E26: HF-01/02/03 | F26: Edge case | G26: Danh sách và tìm kiếm giao dịch | H26: Kiểm tra chức năng mở màn hình Bộ lọc nâng cao khi nhấn nút <Bộ lọc> | I26: Kiểm tra chức năng mở màn hình Bộ lọc nâng cao khi nhấn nút <Bộ lọc> | K26: Kiểm tra hậu điều kiện phân quyền theo CIF: NSD chỉ xem được toàn bộ danh sách giao dịch đề nghị phát hành LC thuộc chính CIF của mình-Thành công-Danh sách và tìm kiếm giao dịch-Kiểm tra hậu điều kiện phân quyền theo CIF: NSD chỉ xem được toàn bộ danh sách giao dịch đề nghị phát hành LC thuộc chính CIF của mình-- | L26: 1 Marker | M26: Pre: - NSD đã đăng nhập và đang ở màn hình danh sách giao dịch phát hành LC Step: 1. NSD nhấn nút <Bộ lọc>. | N26: Hệ thống mở màn hình bộ lọc nâng cao cho NSD nhập điều kiện tìm kiếm. | O26: Medium | S26: Not started
A27: 74 | B27: FO | C27: S01 | D27: Danh sách & tìm kiếm giao dịch | E27: HF-01/02/03 | F27: Edge case | G27: Danh sách và tìm kiếm giao dịch | H27: Kiểm tra chức năng tìm kiếm bằng Bộ lọc nâng cao khi nhập nhiều điều kiện và nhấn <Áp dụng>, đảm bảo điều kiện giữa các trường là quan hệ AND | I27: Kiểm tra chức năng tìm kiếm bằng Bộ lọc nâng cao khi nhập nhiều điều kiện và nhấn <Áp dụng>, đảm bảo điều kiện giữa các trường là quan hệ AND | K27: Kiểm tra chức năng tìm kiếm nhanh (realtime) trên khung tìm kiếm theo trường Mã đề nghị-Thành công-Danh sách và tìm kiếm giao dịch-Kiểm tra chức năng tìm kiếm nhanh (realtime) trên khung tìm kiếm theo trường Mã đề nghị-- | L27: 1 Marker | M27: Pre: - NSD đã đăng nhập, đang ở màn hình danh sách giao dịch phát hành LC và đã mở màn hình bộ lọc nâng cao; có sẵn dữ liệu giao dịch thỏa và không thỏa đồng thời các điều kiện sẽ nhập Step: 1. NSD nhấn nút <Bộ lọc> để mở màn hình bộ lọc nâng cao. 2. NSD nhập đồng thời từ 2 điều kiện tìm kiếm trở lên (ví dụ: Mã đề nghị và Bên nhận LC). 3. NSD nhấn <Áp dụng>. | N27: Hệ thống tìm và hiển thị kết quả tìm kiếm bên dưới, chỉ trả về các giao dịch thỏa mãn đồng thời tất cả các điều kiện đã nhập (quan hệ AND giữa các trường trên khung tìm kiếm). | O27: High | S27: Not started
A28: 75 | B28: FO | C28: S01 | D28: Danh sách & tìm kiếm giao dịch | E28: HF-01/02/03 | F28: Edge case | G28: Danh sách và tìm kiếm giao dịch | H28: Kiểm tra quy tắc tìm kiếm CONTAIN (chứa giá trị nhập) và không phân biệt hoa/thường khi tìm kiếm | I28: Kiểm tra quy tắc tìm kiếm CONTAIN (chứa giá trị nhập) và không phân biệt hoa/thường khi tìm kiếm | K28: Kiểm tra chức năng tìm kiếm nhanh (realtime) trên khung tìm kiếm theo trường Bên nhận LC-Thành công-Danh sách và tìm kiếm giao dịch-Kiểm tra chức năng tìm kiếm nhanh (realtime) trên khung tìm kiếm theo trường Bên nhận LC-- | L28: 1 Marker | M28: Pre: - NSD đã đăng nhập, đang ở màn hình danh sách giao dịch phát hành LC; có sẵn giao dịch mà giá trị trường tìm kiếm chứa chuỗi ký tự dự kiến nhập, viết hoa/thường khác với chuỗi sẽ nhập Step: 1. NSD nhập một chuỗi ký tự chỉ là một phần giá trị của trường tìm kiếm (ví dụ một phần Mã đề nghị), với cách viết hoa/thường khác với dữ liệu gốc trong hệ thống. 2. Quan sát kết quả trả về trên danh sách. | N28: Hệ thống áp dụng quy tắc tìm kiếm "CONTAIN" (có chứa chuỗi nhập) và không phân biệt chữ hoa/chữ thường, trả về đầy đủ các giao dịch có giá trị trường tìm kiếm chứa chuỗi đã nhập bất kể cách viết hoa/thường. | O28: Medium | S28: Not started
A29: 76 | B29: FO | C29: S01 | D29: Danh sách & tìm kiếm giao dịch | E29: HF-01/02/03 | F29: Edge case | G29: Danh sách và tìm kiếm giao dịch | H29: Kiểm tra kết quả tìm kiếm/danh sách được sắp xếp ưu tiên theo Ngày đề nghị giảm dần | I29: Kiểm tra kết quả tìm kiếm/danh sách được sắp xếp ưu tiên theo Ngày đề nghị giảm dần | K29: Kiểm tra chức năng tìm kiếm nhanh (realtime) trên khung tìm kiếm theo trường Số tiền-Thành công-Danh sách và tìm kiếm giao dịch-Kiểm tra chức năng tìm kiếm nhanh (realtime) trên khung tìm kiếm theo trường Số tiền-- | L29: 1 Marker | M29: Pre: - NSD đã đăng nhập, đang ở màn hình danh sách giao dịch phát hành LC; có sẵn nhiều giao dịch với Ngày đề nghị khác nhau Step: 1. NSD vào màn hình danh sách giao dịch phát hành LC (hoặc thực hiện tìm kiếm/lọc ra nhiều kết quả). 2. Quan sát thứ tự các bản ghi hiển thị trên danh sách kết quả. | N29: Kết quả được hiển thị theo thứ tự ưu tiên 1: theo [Ngày đề nghị] giảm dần (giao dịch có Ngày đề nghị mới nhất hiển thị trên cùng). | O29: Medium | S29: Not started
A30: 77 | B30: FO | C30: S01 | D30: Danh sách & tìm kiếm giao dịch | E30: HF-01/02/03 | F30: Edge case | G30: Danh sách và tìm kiếm giao dịch | H30: Kiểm tra chức năng phân trang: hiển thị 10 bản ghi/trang và cho phép xem thêm bản ghi khi còn bản ghi bị ẩn | I30: Kiểm tra chức năng phân trang: hiển thị 10 bản ghi/trang và cho phép xem thêm bản ghi khi còn bản ghi bị ẩn | K30: Kiểm tra chức năng mở màn hình Bộ lọc nâng cao khi nhấn nút <Bộ lọc>-Thành công-Danh sách và tìm kiếm giao dịch-Kiểm tra chức năng mở màn hình Bộ lọc nâng cao khi nhấn nút <Bộ lọc>-- | L30: 1 Marker | M30: Pre: - NSD đã đăng nhập, đang ở màn hình danh sách giao dịch phát hành LC; hệ thống có nhiều hơn 10 giao dịch thỏa điều kiện hiển thị/tìm kiếm Step: 1. NSD vào màn hình danh sách giao dịch phát hành LC (hoặc thực hiện tìm kiếm/lọc ra hơn 10 kết quả). 2. Quan sát số bản ghi hiển thị trên trang đầu tiên. 3. Kiểm tra khu vực phân trang và thực hiện thao tác chọn xem thêm bản ghi. | N30: Hệ thống hiển thị đúng 10 bản ghi cho một trang. Vì còn bản ghi bị ẩn (chưa hiển thị hết), hệ thống hiển thị phân trang, cho phép NSD chọn xem thêm bản ghi tiếp theo. | O30: Medium | S30: Not started
A31: 78 | B31: FO | C31: S01 | D31: Danh sách & tìm kiếm giao dịch | E31: HF-01/02/03 | F31: Edge case | G31: Danh sách và tìm kiếm giao dịch | H31: Kiểm tra thông báo khi tìm kiếm/lọc không có kết quả phù hợp | I31: Kiểm tra thông báo khi tìm kiếm/lọc không có kết quả phù hợp | K31: Kiểm tra chức năng tìm kiếm bằng Bộ lọc nâng cao khi nhập nhiều điều kiện và nhấn <Áp dụng>, đảm bảo điều kiện giữa các trường là quan hệ AND-Thành công-Danh sách và tìm kiếm giao dịch-Kiểm tra chức năng tìm kiếm bằng Bộ lọc nâng cao khi nhập nhiều điều kiện và nhấn <Áp dụng>, đảm bảo điều kiện giữa các trường là quan hệ AND-- | L31: 1 Marker | M31: Pre: - NSD đã đăng nhập, đang ở màn hình danh sách giao dịch phát hành LC Step: 1. NSD nhập điều kiện tìm kiếm trên khung tìm kiếm (hoặc bộ lọc nâng cao rồi nhấn <Áp dụng>) với giá trị không khớp với bất kỳ giao dịch nào trong danh sách. 2. Quan sát kết quả trả về. | N31: Hệ thống không trả về bản ghi nào và hiển thị thông báo MSG2 "Không tìm thấy kết quả phù hợp". | O31: High | S31: Not started
A32: 79 | B32: FO | C32: S01 | D32: Danh sách & tìm kiếm giao dịch | E32: HF-01/02/03 | F32: Edge case | G32: Danh sách và tìm kiếm giao dịch | H32: Thêm mới LC | I32: Kiểm tra chức năng nút "Thêm mới LC" | K32: Kiểm tra quy tắc tìm kiếm CONTAIN (chứa giá trị nhập) và không phân biệt hoa/thường khi tìm kiếm-Thành công-Danh sách và tìm kiếm giao dịch-Kiểm tra quy tắc tìm kiếm CONTAIN (chứa giá trị nhập) và không phân biệt hoa/thường khi tìm kiếm-- | L32: 1 Marker | M32: Step: Tại màn hình, nhấn nút "Thêm mới LC" và quan sát kết quả xử lý. | N32: Hệ thống thực hiện đúng chức năng của nút "Thêm mới LC" theo mô tả nghiệp vụ: Khi chọn, hệ thống mở màn hình Thêm mới đề nghị phát hành | O32: Medium | S32: Not started
A33: 80 | B33: FO | C33: S01 | D33: Danh sách & tìm kiếm giao dịch | E33: HF-01/02/03 | F33: Edge case | G33: Danh sách và tìm kiếm giao dịch | H33: Tìm kiếm | I33: Kiểm tra giới hạn độ dài dữ liệu nhập trường "Tìm kiếm" (tối đa 50 ký tự) | K33: Kiểm tra kết quả tìm kiếm/danh sách được sắp xếp ưu tiên theo Ngày đề nghị giảm dần-Thành công-Danh sách và tìm kiếm giao dịch-Kiểm tra kết quả tìm kiếm/danh sách được sắp xếp ưu tiên theo Ngày đề nghị giảm dần-- | L33: 1 Marker | M33: Step: Nhập giá trị dài hơn 50 ký tự vào trường "Tìm kiếm" và thực hiện Lưu/Gửi duyệt. | N33: Hệ thống không cho nhập quá 50 ký tự hoặc chặn lưu/hiển thị cảnh báo vượt quá độ dài cho phép. | O33: Medium | S33: Not started
A34: 81 | B34: FO | C34: S01 | D34: Danh sách & tìm kiếm giao dịch | E34: HF-01/02/03 | F34: Edge case | G34: Danh sách và tìm kiếm giao dịch | H34: Ngày đề nghị | I34: Kiểm tra định dạng ngày trường "Ngày đề nghị" | K34: Kiểm tra chức năng phân trang: hiển thị 10 bản ghi/trang và cho phép xem thêm bản ghi khi còn bản ghi bị ẩn-Thành công-Danh sách và tìm kiếm giao dịch-Kiểm tra chức năng phân trang: hiển thị 10 bản ghi/trang và cho phép xem thêm bản ghi khi còn bản ghi bị ẩn-- | L34: 1 Marker | M34: Step: Nhập giá trị sai định dạng ngày vào trường "Ngày đề nghị" (ví dụ nhập chữ hoặc ngày không hợp lệ 31/13/2026). | N34: Hệ thống không cho nhập/hiển thị cảnh báo định dạng ngày không hợp lệ. | O34: Medium | S34: Not started
A35: 82 | B35: FO | C35: S01 | D35: Danh sách & tìm kiếm giao dịch | E35: HF-01/02/03 | F35: Edge case | G35: Danh sách và tìm kiếm giao dịch | H35: Ngày đề nghị | I35: Kiểm tra nhập giá trị ngày hợp lệ trường "Ngày đề nghị" | K35: Kiểm tra thông báo khi tìm kiếm/lọc không có kết quả phù hợp-Thành công-Danh sách và tìm kiếm giao dịch-Kiểm tra thông báo khi tìm kiếm/lọc không có kết quả phù hợp-- | L35: 1 Marker | M35: Step: Chọn/nhập 1 giá trị ngày hợp lệ cho trường "Ngày đề nghị" rồi Lưu/Gửi duyệt. | N35: Hệ thống chấp nhận và hiển thị đúng giá trị ngày đã nhập, theo mô tả: Cho phép nhập dữ liệu Nhập trong khoảng Từ ngày – Đến ngày Không cho Từ ngày > Đến ngày | O35: Medium | S35: Not started
A36: 83 | B36: FO | C36: S01 | D36: Danh sách & tìm kiếm giao dịch | E36: HF-01/02/03 | F36: Edge case | G36: Danh sách và tìm kiếm giao dịch | H36: Số tham chiếu LC | I36: Kiểm tra giới hạn độ dài dữ liệu nhập trường "Số tham chiếu LC" (tối đa 20 ký tự) | K36: Thêm mới LC-Thành công-Danh sách và tìm kiếm giao dịch-Kiểm tra chức năng nút "Thêm mới LC"-- | L36: 1 Marker | M36: Step: Nhập giá trị dài hơn 20 ký tự vào trường "Số tham chiếu LC" và thực hiện Lưu/Gửi duyệt. | N36: Hệ thống không cho nhập quá 20 ký tự hoặc chặn lưu/hiển thị cảnh báo vượt quá độ dài cho phép. | O36: Medium | S36: Not started
A37: 84 | B37: FO | C37: S01 | D37: Danh sách & tìm kiếm giao dịch | E37: HF-01/02/03 | F37: Edge case | G37: Danh sách và tìm kiếm giao dịch | H37: Loại LC | I37: Kiểm tra danh sách giá trị lựa chọn của trường "Loại LC" (cập nhật SRS mới: 4 giá trị) | K37: Tìm kiếm-Thành công-Danh sách và tìm kiếm giao dịch-Kiểm tra giới hạn độ dài dữ liệu nhập trường "Tìm kiếm" (tối đa 50 ký tự)-- | L37: 1 Marker | M37: Step: Mở danh sách chọn của trường "Loại LC" và kiểm tra các giá trị hiển thị. | N37: Danh sách hiển thị đầy đủ, đúng 4 giá trị: Regular - UPAS - UPAS PLUS - Discounting (SRS mới bổ sung Discounting). | O37: Medium | S37: Not started
... A42: 89 | B42: FO | C42: S01 | D42: Danh sách & tìm kiếm giao dịch | E42: HF-01/02/03 | F42: Edge case | G42: Danh sách và tìm kiếm giao dịch | H42: Loại tiền LC | I42: Kiểm tra chọn giá trị hợp lệ cho trường "Loại tiền LC" | K42: Loại LC-Thành công-Danh sách và tìm kiếm giao dịch-Kiểm tra chọn giá trị hợp lệ cho trường "Loại LC"-- | L42: 1 Marker | M42: Step: Chọn 1 giá trị hợp lệ trong danh sách trường "Loại tiền LC" rồi Lưu/Gửi duyệt. | N42: Hệ thống chấp nhận giá trị đã chọn, cập nhật/hiển thị đúng theo lựa chọn và các trường phụ thuộc (nếu có) theo mô tả: Giá trị: Chọn đơn vị tiền tệ muốn tìm kiếm. | O42: Medium | S42: Not started
A43: 90 | B43: FO | C43: S01 | D43: Danh sách & tìm kiếm giao dịch | E43: HF-01/02/03 | F43: Edge case | G43: Danh sách và tìm kiếm giao dịch | H43: Trạng thái | I43: Kiểm tra chọn giá trị hợp lệ cho trường "Trạng thái" | K43: Tên khách hàng-Thành công-Danh sách và tìm kiếm giao dịch-Kiểm tra giới hạn độ dài dữ liệu nhập trường "Tên khách hàng" (tối đa 140 ký tự)-- | L43: 1 Marker | M43: Step: Chọn 1 giá trị hợp lệ trong danh sách trường "Trạng thái" rồi Lưu/Gửi duyệt. | N43: Hệ thống chấp nhận giá trị đã chọn, cập nhật/hiển thị đúng theo lựa chọn và các trường phụ thuộc (nếu có) theo mô tả: Giá trị: Tất cả Bản nháp Chờ duyệt Chờ duyệt cấp tiếp theo Chờ ký số pháp nhân Đã gửi ngân hàng Từ chối Ngân hàng từ chối Yêu cầu chỉnh sửa Ngân hàng yêu cầu bổ sung Đã hủy Hoàn thành Mặc định = “Tất | O43: Medium | P43: Cần xác nhận: ký số (USB token/HSM?) | S43: Not started
A44: 91 | B44: FO | C44: S01 | D44: Danh sách & tìm kiếm giao dịch | E44: HF-01/02/03 | F44: Edge case | G44: Danh sách và tìm kiếm giao dịch | H44: Áp dụng | I44: Kiểm tra chức năng nút "Áp dụng" | K44: Tên bên thụ hưởng-Thành công-Danh sách và tìm kiếm giao dịch-Kiểm tra giới hạn độ dài dữ liệu nhập trường "Tên bên thụ hưởng" (tối đa 140 ký tự)-- | L44: 1 Marker | M44: Step: Tại màn hình, nhấn nút "Áp dụng" và quan sát kết quả xử lý. | N44: Hệ thống thực hiện đúng chức năng của nút "Áp dụng" theo mô tả nghiệp vụ: Khi chọn, hệ thống tìm kiếm theo điều kiện đã nhập và trả về kết quả tìm kiếm | O44: Medium | S44: Not started
A45: 92 | B45: FO | C45: S01 | D45: Danh sách & tìm kiếm giao dịch | E45: HF-01/02/03 | F45: Edge case | G45: Danh sách và tìm kiếm giao dịch | H45: Xóa bộ lọc | I45: Kiểm tra chức năng nút "Xóa bộ lọc" | K45: Số tiền LC-Thành công-Danh sách và tìm kiếm giao dịch-Kiểm tra định dạng dữ liệu số trường "Số tiền LC"-- | L45: 1 Marker | M45: Step: Tại màn hình, nhấn nút "Xóa bộ lọc" và quan sát kết quả xử lý. | N45: Hệ thống thực hiện đúng chức năng của nút "Xóa bộ lọc" theo mô tả nghiệp vụ: Khi chọn, hệ thống xóa kết quả tìm kiếm và điều kiện tìm kiếm trước đó | O45: Medium | S45: Not started
A46: 93 | B46: FO | C46: S01 | D46: Danh sách & tìm kiếm giao dịch | E46: HF-01/02/03 | F46: Edge case | G46: Danh sách và tìm kiếm giao dịch | H46: STT | I46: Kiểm tra hiển thị trường "STT" | K46: Loại tiền LC-Thành công-Danh sách và tìm kiếm giao dịch-Kiểm tra chọn giá trị hợp lệ cho trường "Loại tiền LC"-- | L46: 1 Marker | M46: Step: Truy cập màn hình và quan sát trường "STT". | N46: Trường "STT" hiển thị đúng nội dung/nhãn theo mô tả: Hệ thống tự động đánh số tăng dần | O46: Low | S46: Not started
A47: 94 | B47: FO | C47: S01 | D47: Danh sách & tìm kiếm giao dịch | E47: HF-01/02/03 | F47: Edge case | G47: Danh sách và tìm kiếm giao dịch | H47: Mã giao dịch | I47: Kiểm tra nhập/hiển thị dữ liệu hợp lệ trường "Mã giao dịch" | K47: Trạng thái-Thành công-Danh sách và tìm kiếm giao dịch-Kiểm tra chọn giá trị hợp lệ cho trường "Trạng thái"-- | L47: 1 Marker | M47: Step: Nhập/chọn giá trị hợp lệ cho trường "Mã giao dịch" theo mô tả nghiệp vụ rồi thực hiện Lưu/Gửi duyệt. | N47: Hệ thống chấp nhận và xử lý đúng theo mô tả: Hiển thị [Mã đề nghị] tương ứng | O47: Medium | S47: Not started | U47: Phục hồi
A48: 95 | B48: FO | C48: S01 | D48: Danh sách & tìm kiếm giao dịch | E48: HF-01/02/03 | F48: Edge case | G48: Danh sách và tìm kiếm giao dịch | H48: Số tham chiếu LC | I48: Kiểm tra hiển thị trường "Số tham chiếu LC" | K48: Áp dụng-Thành công-Danh sách và tìm kiếm giao dịch-Kiểm tra chức năng nút "Áp dụng"-- | L48: 1 Marker | M48: Step: Truy cập màn hình và quan sát trường "Số tham chiếu LC". | N48: Trường "Số tham chiếu LC" hiển thị đúng nội dung/nhãn theo mô tả: Hiển thị số tham chiếu LC. Số LC ref trên TI. | O48: Low | S48: Not started
A49: 96 | B49: FO | C49: S01 | D49: Danh sách & tìm kiếm giao dịch | E49: HF-01/02/03 | F49: Edge case | G49: Danh sách và tìm kiếm giao dịch | H49: Loại LC | I49: Kiểm tra hiển thị trường "Loại LC" | K49: Xóa bộ lọc-Thành công-Danh sách và tìm kiếm giao dịch-Kiểm tra chức năng nút "Xóa bộ lọc"-- | L49: 1 Marker | M49: Step: Truy cập màn hình và quan sát trường "Loại LC". | N49: Trường "Loại LC" hiển thị đúng nội dung/nhãn theo mô tả: Hiển thị [Loại LC] tương ứng | O49: Low | S49: Not started
A50: 97 | B50: FO | C50: S01 | D50: Danh sách & tìm kiếm giao dịch | E50: HF-01/02/03 | F50: Edge case | G50: Danh sách và tìm kiếm giao dịch | H50: Ngày đề nghị | I50: Kiểm tra hiển thị trường "Ngày đề nghị" | K50: STT-Thành công-Danh sách và tìm kiếm giao dịch-Kiểm tra hiển thị trường "STT"-- | L50: 1 Marker | M50: Step: Truy cập màn hình và quan sát trường "Ngày đề nghị". | N50: Trường "Ngày đề nghị" hiển thị đúng nội dung/nhãn theo mô tả: Hiển thị [Ngày đề nghị] tương ứng Format: dd/mm/yyyy Ngày Maker gửi duyệt giao dịch. | O50: Low | S50: Not started
A51: 98 | B51: FO | C51: S01 | D51: Danh sách & tìm kiếm giao dịch | E51: HF-01/02/03 | F51: Edge case | G51: Danh sách và tìm kiếm giao dịch | H51: Số CIF | I51: Kiểm tra hiển thị trường "Số CIF" | K51: Mã giao dịch-Thành công-Danh sách và tìm kiếm giao dịch-Kiểm tra nhập/hiển thị dữ liệu hợp lệ trường "Mã giao dịch"-- | L51: 1 Marker | M51: Step: Truy cập màn hình và quan sát trường "Số CIF". | N51: Trường "Số CIF" hiển thị đúng nội dung/nhãn theo mô tả: Hiển thị số CIF | O51: Low | S51: Not started
A52: 99 | B52: FO | C52: S01 | D52: Danh sách & tìm kiếm giao dịch | E52: HF-01/02/03 | F52: Edge case | G52: Danh sách và tìm kiếm giao dịch | H52: Tên khách hàng | I52: Kiểm tra hiển thị trường "Tên khách hàng" | K52: Số tham chiếu LC-Thành công-Danh sách và tìm kiếm giao dịch-Kiểm tra hiển thị trường "Số tham chiếu LC"-- | L52: 1 Marker | M52: Step: Truy cập màn hình và quan sát trường "Tên khách hàng". | N52: Trường "Tên khách hàng" hiển thị đúng nội dung/nhãn theo mô tả: Hiển thị tên khách hàng | O52: Low | S52: Not started
A53: 100 | B53: FO | C53: S01 | D53: Danh sách & tìm kiếm giao dịch | E53: HF-01/02/03 | F53: Edge case | G53: Danh sách và tìm kiếm giao dịch | H53: Tên bên thụ hưởng | I53: Kiểm tra hiển thị trường "Tên bên thụ hưởng" | K53: Loại LC-Thành công-Danh sách và tìm kiếm giao dịch-Kiểm tra hiển thị trường "Loại LC"-- | L53: 1 Marker | M53: Step: Truy cập màn hình và quan sát trường "Tên bên thụ hưởng". | N53: Trường "Tên bên thụ hưởng" hiển thị đúng nội dung/nhãn theo mô tả: Hiển thị tên bên thụ hưởng. | O53: Low | S53: Not started
A54: 101 | B54: FO | C54: S01 | D54: Danh sách & tìm kiếm giao dịch | E54: HF-01/02/03 | F54: Edge case | G54: Danh sách và tìm kiếm giao dịch | H54: Số hợp đồng | I54: Kiểm tra hiển thị trường "Số hợp đồng" | K54: Ngày đề nghị-Thành công-Danh sách và tìm kiếm giao dịch-Kiểm tra hiển thị trường "Ngày đề nghị"-- | L54: 1 Marker | M54: Step: Truy cập màn hình và quan sát trường "Số hợp đồng". | N54: Trường "Số hợp đồng" hiển thị đúng nội dung/nhãn theo mô tả: Hiển thị [Số hợp đồng] (Sale contract). | O54: Low | S54: Not started
A55: 102 | B55: FO | C55: S01 | D55: Danh sách & tìm kiếm giao dịch | E55: HF-01/02/03 | F55: Edge case | G55: Danh sách và tìm kiếm giao dịch | H55: Ngày hết hạn | I55: Kiểm tra hiển thị trường "Ngày hết hạn" | K55: Số CIF-Thành công-Danh sách và tìm kiếm giao dịch-Kiểm tra hiển thị trường "Số CIF"-- | L55: 1 Marker | M55: Step: Truy cập màn hình và quan sát trường "Ngày hết hạn". | N55: Trường "Ngày hết hạn" hiển thị đúng nội dung/nhãn theo mô tả: Hiển thị [Ngày hết hạn] tương ứng Format: dd/mm/yyyy | O55: Low | S55: Not started
A56: 103 | B56: FO | C56: S01 | D56: Danh sách & tìm kiếm giao dịch | E56: HF-01/02/03 | F56: Edge case | G56: Danh sách và tìm kiếm giao dịch | H56: Trạng thái | I56: Kiểm tra hiển thị trường "Trạng thái" | K56: Tên khách hàng-Thành công-Danh sách và tìm kiếm giao dịch-Kiểm tra hiển thị trường "Tên khách hàng"-- | L56: 1 Marker | M56: Step: Truy cập màn hình và quan sát trường "Trạng thái". | N56: Trường "Trạng thái" hiển thị đúng nội dung/nhãn theo mô tả: Hiển thị [Trạng thái] tương ứng | O56: Low | S56: Not started
A57: 104 | B57: FO | C57: S01 | D57: Danh sách & tìm kiếm giao dịch | E57: HF-01/02/03 | F57: Edge case | G57: Danh sách và tìm kiếm giao dịch | H57: Đề nghị mỗi trang | I57: Kiểm tra chọn giá trị hợp lệ cho trường "Đề nghị mỗi trang" | K57: Tên bên thụ hưởng-Thành công-Danh sách và tìm kiếm giao dịch-Kiểm tra hiển thị trường "Tên bên thụ hưởng"-- | L57: 1 Marker | M57: Step: Chọn 1 giá trị hợp lệ trong danh sách trường "Đề nghị mỗi trang" rồi Lưu/Gửi duyệt. | N57: Hệ thống chấp nhận giá trị đã chọn, cập nhật/hiển thị đúng theo lựa chọn và các trường phụ thuộc (nếu có) theo mô tả: Giá trị: 10 20 50 Mặc định = “10” | O57: Medium | S57: Not started
A58: 105 | B58: FO | C58: S01 | D58: Danh sách & tìm kiếm giao dịch | E58: HF-01/02/03 | F58: Edge case | G58: Danh sách và tìm kiếm giao dịch | H58: Phân trang | I58: Kiểm tra nhập/hiển thị dữ liệu hợp lệ trường "Phân trang" | K58: Số hợp đồng-Thành công-Danh sách và tìm kiếm giao dịch-Kiểm tra hiển thị trường "Số hợp đồng"-- | L58: 1 Marker | M58: Step: Nhập/chọn giá trị hợp lệ cho trường "Phân trang" theo mô tả nghiệp vụ rồi thực hiện Lưu/Gửi duyệt. | N58: Hệ thống chấp nhận và xử lý đúng theo mô tả: Hiển thị mỗi 10 bản ghi cho một trang Nhấn số trang, hệ thống mở trang tương ứng Nhấn icon <>, hệ thống chuyển tiếp trang sau hoặc trước | O58: Medium | S58: Not started
A59: 106 | B59: FO | C59: S01 | D59: Danh sách & tìm kiếm giao dịch | E59: HF-01/02/03 | F59: Edge case | G59: Danh sách và tìm kiếm giao dịch | H59: Tạo mới L/C | I59: Kiểm tra nhập/hiển thị dữ liệu hợp lệ trường "Tạo mới L/C" | K59: Ngày hết hạn-Thành công-Danh sách và tìm kiếm giao dịch-Kiểm tra hiển thị trường "Ngày hết hạn"-- | L59: 1 Marker | M59: Step: Nhập/chọn giá trị hợp lệ cho trường "Tạo mới L/C" theo mô tả nghiệp vụ rồi thực hiện Lưu/Gửi duyệt. | N59: Hệ thống chấp nhận và xử lý đúng theo mô tả: Bấm vào sẽ hiển thị các lựa chọn để phát hành LC. 1.eForm 2.Template mẫu 3.Tư vấn phát hành LC 4.Tải file 5.Copy từ LC Bấm copy từ LC sẽ dẫn đến màn hình Popup thông báo: “Vui lòng tìm kiếm mã đề nghị ở danh sách để thực hiện sao chép hồ sơ.” | O59: Medium | S59: Not started
... A67: 114 | B67: FO | C67: S01 | D67: Danh sách & tìm kiếm giao dịch | E67: HF-01/02/03 | F67: Edge case | G67: Danh sách và tìm kiếm giao dịch | H67: Đề nghị mỗi trang | I67: Kiểm tra giá trị mặc định của trường "Đề nghị mỗi trang" khi truy cập màn hình lần đầu (chưa thao tác chọn) | K67: Tên khách hàng-Thành công-Danh sách và tìm kiếm giao dịch-Kiểm tra quy tắc "Không cho phép nhập khoảng trắng" đối với trường "Tên khách hàng"-- | L67: 1 Marker | M67: Pre: - User truy cập màn hình Danh sách và tìm kiếm giao dịch lần đầu, chưa thao tác chọn số bản ghi/trang. Step: 1. Quan sát giá trị đang được chọn sẵn tại trường "Đề nghị mỗi trang" và số bản ghi thực tế đang hiển thị trên 1 trang. | N67: Trường "Đề nghị mỗi trang" hiển thị giá trị mặc định đã chọn sẵn = "10", danh sách hiển thị tối đa 10 bản ghi/trang. | O67: Medium | S67: Not started
A68: 115 | B68: FO | C68: S18 | D68: Xem chi tiết | E68: HF-01/02/03 | F68: Edge case | G68: Xem chi tiết | H68: Kiểm tra quyền truy cập chức năng "Xem chi tiết" (FO) | I68: Kiểm tra quyền truy cập chức năng "Xem chi tiết" (FO) | K68: Tên bên thụ hưởng-Thành công-Danh sách và tìm kiếm giao dịch-Kiểm tra quy tắc "Không cho phép nhập khoảng trắng" đối với trường "Tên bên thụ hưởng"-- | L68: 1 Marker | M68: Step: Đăng nhập hệ thống với user được phân quyền (Maker/Checker/Viewer được phân quyền chức năng Phát hành LC), truy cập theo đường dẫn menu tương ứng chức năng "Xem chi tiết". | N68: User truy cập được chức năng "Xem chi tiết", hệ thống mở đúng màn hình xem chi tiết giao dịch. | O68: High | S68: Not started | U68: Phục hồi
A69: 116 | B69: FO | C69: S18 | D69: Xem chi tiết | E69: HF-01/02/03 | F69: Edge case | G69: Xem chi tiết | H69: Kiểm tra chặn truy cập chức năng "Xem chi tiết" (FO) khi không được phân quyền | I69: Kiểm tra chặn truy cập chức năng "Xem chi tiết" (FO) khi không được phân quyền | K69: Số tiền LC-Thành công-Danh sách và tìm kiếm giao dịch-Kiểm tra giới hạn số chữ số nhập trường "Số tiền LC" tại bộ lọc tìm kiếm (tối đa 16 chữ số phần nguyên, 2 chữ số thập phân)-- | L69: 1 Marker | M69: Pre: - Đề nghị LC đã Gửi duyệt (đã cộng vào hạn mức sử dụng trong ngày); Hạn mức sử dụng trong ngày hiện tại = X (đã bao gồm số tiền LC = Y của đề nghị này). Step: 1. Thực hiện thao tác Từ chối (DN từ chối) hoặc NH từ chối đối với đề nghị LC. | N69: Hệ thống tự động cập nhật số tiền = - số tiền LC, tức Hạn mức sử dụng trong ngày mới = X - Y, và cập nhật vào trường Hạn mức sử dụng trong ngày trong DB. | O69: High | S69: Not started
A70: 117 | B70: FO | C70: S18 | D70: Xem chi tiết | E70: HF-01/02/03 | F70: Edge case | G70: Xem chi tiết | H70: Kiểm tra hệ thống thực hiện phân quyền đúng theo cây phân quyền (TTTM > LCNK > Phát hành LC (PHLC) > Truy vấn hồ sơ (V_PHLC)) khi user đăng nhập thành công và cho phép xem màn hình chi tiết Phát hành LC | I70: Kiểm tra hệ thống thực hiện phân quyền đúng theo cây phân quyền (TTTM > LCNK > Phát hành LC (PHLC) > Truy vấn hồ sơ (V_PHLC)) khi user đăng nhập thành công và cho phép xem màn hình chi tiết Phát hành LC | K70: Trạng thái-Thành công-Danh sách và tìm kiếm giao dịch-Kiểm tra giá trị mặc định của trường "Trạng thái" khi truy cập màn hình lần đầu (chưa thao tác chọn)-- | L70: 1 Marker | M70: Pre: - User thuộc doanh nghiệp (DN) đã được cấp quyền V_PHLC (Truy vấn hồ sơ) trong cây phân quyền trên BO Admin Portal; đã có tồn tại 1 hồ sơ đề nghị Phát hành LC trên hệ thống Step: 1. Đăng nhập thành công vào hệ thống bằng user đã được cấp quyền V_PHLC. 2. Quan sát hệ thống gọi API tới BO Admin Portal để lấy thông tin CIF, Permission (cây phân quyền), roleName của user. 3. Từ danh sách hồ sơ Phát hành LC, chọn 1 hồ sơ bất kỳ để xem chi tiết. | N70: Hệ thống lấy đúng thông tin CIF (thuộc DN đang login), Permission (cây phân quyền 4 tầng TTTM > LCNK > Phát hành LC (Mã PHLC) > Truy vấn hồ sơ (Mã V_PHLC)) và roleName từ BO Admin Portal - hệ thống hiển thị màn hình cho phép người dùng xem thông tin chi tiết hồ sơ Phát hành LC. | O70: High | P70: Cần xác nhận: gọi API ngoài | S70: Not started
A71: 118 | B71: FO | C71: S18 | D71: Xem chi tiết | E71: HF-01/02/03 | F71: Edge case | G71: Xem chi tiết | H71: Kiểm tra hiển thị trường [Lý do từ chối] khi hồ sơ có trạng thái = Từ chối và bị từ chối bởi người dùng DN | I71: Kiểm tra hiển thị trường [Lý do từ chối] khi hồ sơ có trạng thái = Từ chối và bị từ chối bởi người dùng DN | K71: Đề nghị mỗi trang-Thành công-Danh sách và tìm kiếm giao dịch-Kiểm tra giá trị mặc định của trường "Đề nghị mỗi trang" khi truy cập màn hình lần đầu (chưa thao tác chọn)-- | L71: 1 Marker | M71: Pre: - Tồn tại 1 hồ sơ đề nghị Phát hành LC có trạng thái = Từ chối, được từ chối bởi một người dùng thuộc DN (ví dụ người phê duyệt phía DN) Step: 1. Đăng nhập hệ thống bằng user có quyền xem chi tiết. 2. Mở màn hình xem chi tiết của hồ sơ có trạng thái = Từ chối (bị từ chối bởi người dùng DN). 3. Quan sát trường [Lý do từ chối] trên màn hình. | N71: Hệ thống hiển thị trường [Lý do từ chối] với nội dung theo đúng định dạng: "[Tên người Từ chối]: [Lý do từ chối]". | O71: High | S71: Not started
A72: 119 | B72: FO | C72: S18 | D72: Xem chi tiết | E72: HF-01/02/03 | F72: Edge case | G72: Xem chi tiết | H72: Kiểm tra hiển thị trường [Lý do từ chối] khi hồ sơ có trạng thái = Từ chối và bị từ chối bởi người dùng Ngân hàng | I72: Kiểm tra hiển thị trường [Lý do từ chối] khi hồ sơ có trạng thái = Từ chối và bị từ chối bởi người dùng Ngân hàng | K72: Kiểm tra quyền truy cập chức năng "Xem chi tiết" (FO)-Thành công-Xem chi tiết-Kiểm tra quyền truy cập chức năng "Xem chi tiết" (FO)-- | L72: 1 Marker | M72: Pre: - Tồn tại 1 hồ sơ đề nghị Phát hành LC có trạng thái = Từ chối, được từ chối bởi người dùng phía Ngân hàng Step: 1. Đăng nhập hệ thống bằng user có quyền xem chi tiết. 2. Mở màn hình xem chi tiết của hồ sơ có trạng thái = Từ chối (bị từ chối bởi người dùng Ngân hàng). 3. Quan sát trường [Lý do từ chối] trên màn hình. | N72: Hệ thống hiển thị trường [Lý do từ chối] với nội dung theo đúng định dạng: "Ngân hàng: [Lý do từ chối]". | O72: High | S72: Not started
A73: 120 | B73: FO | C73: S18 | D73: Xem chi tiết | E73: HF-01/02/03 | F73: Edge case | G73: Xem chi tiết | H73: Kiểm tra trường [Lý do từ chối] không hiển thị khi hồ sơ không ở trạng thái = Từ chối | I73: Kiểm tra trường [Lý do từ chối] không hiển thị khi hồ sơ không ở trạng thái = Từ chối | K73: Kiểm tra chặn truy cập chức năng "Xem chi tiết" (FO) khi không được phân quyền-Thành công-Xem chi tiết-Kiểm tra chặn truy cập chức năng "Xem chi tiết" (FO) khi không được phân quyền-- | L73: 1 Marker | M73: Pre: - Tồn tại 1 hồ sơ đề nghị Phát hành LC có trạng thái khác Từ chối (ví dụ: Bản nháp, Chờ duyệt, Đã duyệt...) Step: 1. Đăng nhập hệ thống bằng user có quyền xem chi tiết. 2. Mở màn hình xem chi tiết của hồ sơ có trạng thái khác Từ chối. 3. Quan sát màn hình chi tiết. | N73: Hệ thống không hiển thị trường [Lý do từ chối] trên màn hình xem chi tiết (theo mô tả BR, trường này chỉ hiển thị khi trạng thái = Từ chối). | O73: Medium | S73: Not started
A74: 121 | B74: FO | C74: S18 | D74: Xem chi tiết | E74: HF-01/02/03 | F74: Edge case | G74: Xem chi tiết | H74: Kiểm tra chức năng nút <Lịch sử giao dịch> mở tab xem chi tiết thông tin ghi nhận thay đổi của giao dịch | I74: Kiểm tra chức năng nút <Lịch sử giao dịch> mở tab xem chi tiết thông tin ghi nhận thay đổi của giao dịch | K74: Kiểm tra hệ thống thực hiện phân quyền đúng theo cây phân quyền (TTTM > LCNK > Phát hành LC (PHLC) > Truy vấn hồ sơ (V_PHLC)) khi user đăng nhập thành công và cho phép xem màn hình chi tiết Phát hành LC-Thành công-Xem chi tiết-Kiểm tra hệ thống thực hiện phân quyền đúng theo cây phân quyền (TTTM > LCNK > Phát hành LC (PHLC) > Truy vấn hồ sơ (V_PHLC)) khi user đăng nhập thành công và cho phép xem màn hình chi tiết Phát hành LC-- | L74: 1 Marker | M74: Pre: - Tồn tại 1 hồ sơ đề nghị Phát hành LC đã trải qua nhiều hành động (tạo mới, chỉnh sửa, lưu nháp, phê duyệt, từ chối, ký số cá nhân, ký số pháp nhân, hủy đề nghị, NH từ chối, NH yêu cầu bổ sung) Step: 1. Đăng nhập hệ thống bằng user có quyền xem chi tiết. 2. Mở màn hình xem chi tiết hồ sơ nêu trên. 3. Chọn <Lịch sử giao dịch>. | N74: Hệ thống mở tab xem chi tiết thông tin ghi nhận thay đổi của giao dịch, bao gồm đầy đủ các hành động: Tạo mới, Chỉnh sửa, Lưu nháp, Phê duyệt, Từ chối, Ký số cá nhân, Ký số pháp nhân, Hủy đề nghị, NH từ chối, NH yêu cầu bổ sung. | O74: Medium | P74: Cần xác nhận: ký số (USB token/HSM?) | S74: Not started
A75: 122 | B75: FO | C75: S18 | D75: Xem chi tiết | E75: HF-01/02/03 | F75: Edge case | G75: Xem chi tiết | H75: Kiểm tra chức năng nút <Đóng> đóng màn hình xem chi tiết và quay lại màn hình trước đó | I75: Kiểm tra chức năng nút <Đóng> đóng màn hình xem chi tiết và quay lại màn hình trước đó | K75: Kiểm tra hiển thị trường [Lý do từ chối] khi hồ sơ có trạng thái = Từ chối và bị từ chối bởi người dùng DN-Thành công-Xem chi tiết-Kiểm tra hiển thị trường [Lý do từ chối] khi hồ sơ có trạng thái = Từ chối và bị từ chối bởi người dùng DN-- | L75: 1 Marker | M75: Pre: - Đang ở màn hình xem chi tiết hồ sơ Phát hành LC (điều hướng từ màn hình danh sách/màn hình trước đó) Step: 1. Đăng nhập hệ thống bằng user có quyền xem chi tiết. 2. Từ một màn hình bất kỳ (ví dụ danh sách hồ sơ), mở màn hình xem chi tiết 1 hồ sơ. 3. Chọn <Đóng>. | N75: Hệ thống đóng màn hình xem chi tiết hiện tại và quay lại đúng màn hình trước đó. | O75: Medium | S75: Not started
A76: 123 | B76: FO | C76: S18 | D76: Xem chi tiết | E76: HF-01/02/03 | F76: Edge case | G76: Xem chi tiết | H76: Kiểm tra nút <Chỉnh sửa> hiển thị và hoạt động đúng khi hồ sơ có trạng thái = Bản nháp | I76: Kiểm tra nút <Chỉnh sửa> hiển thị và hoạt động đúng khi hồ sơ có trạng thái = Bản nháp | K76: Kiểm tra hiển thị trường [Lý do từ chối] khi hồ sơ có trạng thái = Từ chối và bị từ chối bởi người dùng Ngân hàng-Thành công-Xem chi tiết-Kiểm tra hiển thị trường [Lý do từ chối] khi hồ sơ có trạng thái = Từ chối và bị từ chối bởi người dùng Ngân hàng-- | L76: 1 Marker | M76: Pre: - Tồn tại 1 hồ sơ đề nghị Phát hành LC có trạng thái = Bản nháp Step: 1. Đăng nhập hệ thống bằng user có quyền xem chi tiết. 2. Mở màn hình xem chi tiết hồ sơ có trạng thái = Bản nháp. 3. Quan sát nút <Chỉnh sửa> và chọn <Chỉnh sửa>. | N76: Nút <Chỉnh sửa> hiển thị trên màn hình (do TT = Bản nháp). Khi chọn, hệ thống mở màn hình cho phép chỉnh sửa đề nghị (theo mục II.1.2.4. Chỉnh sửa). | O76: High | S76: Not started
A77: 124 | B77: FO | C77: S18 | D77: Xem chi tiết | E77: HF-01/02/03 | F77: Edge case | G77: Xem chi tiết | H77: Kiểm tra nút <Chỉnh sửa> hiển thị và hoạt động đúng khi hồ sơ có trạng thái = Yêu cầu bổ sung | I77: Kiểm tra nút <Chỉnh sửa> hiển thị và hoạt động đúng khi hồ sơ có trạng thái = Yêu cầu bổ sung | K77: Kiểm tra trường [Lý do từ chối] không hiển thị khi hồ sơ không ở trạng thái = Từ chối-Thành công-Xem chi tiết-Kiểm tra trường [Lý do từ chối] không hiển thị khi hồ sơ không ở trạng thái = Từ chối-- | L77: 1 Marker | M77: Pre: - Tồn tại 1 hồ sơ đề nghị Phát hành LC có trạng thái = Yêu cầu bổ sung Step: 1. Đăng nhập hệ thống bằng user có quyền xem chi tiết. 2. Mở màn hình xem chi tiết hồ sơ có trạng thái = Yêu cầu bổ sung. 3. Quan sát nút <Chỉnh sửa> và chọn <Chỉnh sửa>. | N77: Nút <Chỉnh sửa> hiển thị trên màn hình (do TT = Yêu cầu bổ sung). Khi chọn, hệ thống mở màn hình cho phép chỉnh sửa đề nghị (theo mục II.1.2.4. Chỉnh sửa). | O77: High | S77: Not started
A78: 125 | B78: FO | C78: S18 | D78: Xem chi tiết | E78: HF-01/02/03 | F78: Edge case | G78: Xem chi tiết | H78: Kiểm tra nút <Chỉnh sửa> không hiển thị khi hồ sơ ở trạng thái khác Bản nháp/Yêu cầu bổ sung | I78: Kiểm tra nút <Chỉnh sửa> không hiển thị khi hồ sơ ở trạng thái khác Bản nháp/Yêu cầu bổ sung | K78: Kiểm tra chức năng nút <Lịch sử giao dịch> mở tab xem chi tiết thông tin ghi nhận thay đổi của giao dịch-Thành công-Xem chi tiết-Kiểm tra chức năng nút <Lịch sử giao dịch> mở tab xem chi tiết thông tin ghi nhận thay đổi của giao dịch-- | L78: 1 Marker | M78: Pre: - Tồn tại 1 hồ sơ đề nghị Phát hành LC có trạng thái khác Bản nháp và Yêu cầu bổ sung (ví dụ: Chờ duyệt, Đã duyệt, Từ chối) Step: 1. Đăng nhập hệ thống bằng user có quyền xem chi tiết. 2. Mở màn hình xem chi tiết hồ sơ có trạng thái khác Bản nháp/Yêu cầu bổ sung. 3. Quan sát khu vực các nút chức năng trên màn hình. | N78: Nút <Chỉnh sửa> không hiển thị trên màn hình (do BR quy định nút chỉ hiển thị với TT = Bản nháp, Yêu cầu bổ sung). | O78: Medium | S78: Not started
A79: 126 | B79: FO | C79: S18 | D79: Xem chi tiết | E79: HF-01/02/03 | F79: Edge case | G79: Xem chi tiết | H79: Kiểm tra nút <Xóa đề nghị> hiển thị và mở popup xác nhận xóa khi hồ sơ có trạng thái = Bản nháp | I79: Kiểm tra nút <Xóa đề nghị> hiển thị và mở popup xác nhận xóa khi hồ sơ có trạng thái = Bản nháp | K79: Kiểm tra chức năng nút <Đóng> đóng màn hình xem chi tiết và quay lại màn hình trước đó-Thành công-Xem chi tiết-Kiểm tra chức năng nút <Đóng> đóng màn hình xem chi tiết và quay lại màn hình trước đó-- | L79: 1 Marker | M79: Pre: - Tồn tại 1 hồ sơ đề nghị Phát hành LC có trạng thái = Bản nháp Step: 1. Đăng nhập hệ thống bằng user có quyền xem chi tiết. 2. Mở màn hình xem chi tiết hồ sơ có trạng thái = Bản nháp. 3. Quan sát nút <Xóa đề nghị> và chọn <Xóa đề nghị>. | N79: Nút <Xóa đề nghị> hiển thị trên màn hình (do TT = Bản nháp). Khi chọn, hệ thống mở Popup xác nhận xóa đề nghị (theo mục II.1.2.5. Xóa đề nghị). | O79: High | S79: Not started
A80: 127 | B80: FO | C80: S18 | D80: Xem chi tiết | E80: HF-01/02/03 | F80: Edge case | G80: Xem chi tiết | H80: Kiểm tra nút <Xóa đề nghị> không hiển thị khi hồ sơ ở trạng thái khác Bản nháp | I80: Kiểm tra nút <Xóa đề nghị> không hiển thị khi hồ sơ ở trạng thái khác Bản nháp | K80: Kiểm tra nút <Chỉnh sửa> hiển thị và hoạt động đúng khi hồ sơ có trạng thái = Bản nháp-Thành công-Xem chi tiết-Kiểm tra nút <Chỉnh sửa> hiển thị và hoạt động đúng khi hồ sơ có trạng thái = Bản nháp-- | L80: 1 Marker | M80: Pre: - Tồn tại 1 hồ sơ đề nghị Phát hành LC có trạng thái khác Bản nháp Step: 1. Đăng nhập hệ thống bằng user có quyền xem chi tiết. 2. Mở màn hình xem chi tiết hồ sơ có trạng thái khác Bản nháp. 3. Quan sát khu vực các nút chức năng trên màn hình. | N80: Nút <Xóa đề nghị> không hiển thị trên màn hình (do BR quy định nút chỉ hiển thị với TT = Bản nháp). | O80: Medium | S80: Not started
A81: 128 | B81: FO | C81: S18 | D81: Xem chi tiết | E81: HF-01/02/03 | F81: Edge case | G81: Xem chi tiết | H81: Kiểm tra nút <Hủy giao dịch> hiển thị và mở popup xác nhận hủy đề nghị khi hồ sơ có trạng thái = Yêu cầu bổ sung | I81: Kiểm tra nút <Hủy giao dịch> hiển thị và mở popup xác nhận hủy đề nghị khi hồ sơ có trạng thái = Yêu cầu bổ sung | K81: Kiểm tra nút <Chỉnh sửa> hiển thị và hoạt động đúng khi hồ sơ có trạng thái = Yêu cầu bổ sung-Thành công-Xem chi tiết-Kiểm tra nút <Chỉnh sửa> hiển thị và hoạt động đúng khi hồ sơ có trạng thái = Yêu cầu bổ sung-- | L81: 1 Marker | M81: Pre: - Tồn tại 1 hồ sơ đề nghị Phát hành LC có trạng thái = Yêu cầu bổ sung Step: 1. Đăng nhập hệ thống bằng user có quyền xem chi tiết. 2. Mở màn hình xem chi tiết hồ sơ có trạng thái = Yêu cầu bổ sung. 3. Quan sát nút <Hủy giao dịch> và chọn <Hủy giao dịch>. | N81: Nút <Hủy giao dịch> hiển thị trên màn hình (do TT = Yêu cầu bổ sung). Khi chọn, hệ thống mở Popup xác nhận hủy đề nghị (theo mục II.1.2.6. Hủy đề nghị). | O81: High | S81: Not started
A82: 129 | B82: FO | C82: S18 | D82: Xem chi tiết | E82: HF-01/02/03 | F82: Edge case | G82: Xem chi tiết | H82: Kiểm tra nút <Hủy giao dịch> không hiển thị khi hồ sơ ở trạng thái khác Yêu cầu bổ sung | I82: Kiểm tra nút <Hủy giao dịch> không hiển thị khi hồ sơ ở trạng thái khác Yêu cầu bổ sung | K82: Kiểm tra nút <Chỉnh sửa> không hiển thị khi hồ sơ ở trạng thái khác Bản nháp/Yêu cầu bổ sung-Thành công-Xem chi tiết-Kiểm tra nút <Chỉnh sửa> không hiển thị khi hồ sơ ở trạng thái khác Bản nháp/Yêu cầu bổ sung-- | L82: 1 Marker | M82: Pre: - Tồn tại 1 hồ sơ đề nghị Phát hành LC có trạng thái khác Yêu cầu bổ sung Step: 1. Đăng nhập hệ thống bằng user có quyền xem chi tiết. 2. Mở màn hình xem chi tiết hồ sơ có trạng thái khác Yêu cầu bổ sung. 3. Quan sát khu vực các nút chức năng trên màn hình. | N82: Nút <Hủy giao dịch> không hiển thị trên màn hình (do BR quy định nút chỉ hiển thị với TT = Yêu cầu bổ sung). | O82: Medium | S82: Not started
A83: 130 | B83: FO | C83: S18 | D83: Xem chi tiết | E83: HF-01/02/03 | F83: Edge case | G83: Xem chi tiết | H83: Trạng thái | I83: Kiểm tra nút <Sao chép> hiển thị và mở popup xác nhận sao chép khi hồ sơ ở trạng thái khác Bản nháp | K83: Kiểm tra nút <Xóa đề nghị> hiển thị và mở popup xác nhận xóa khi hồ sơ có trạng thái = Bản nháp-Thành công-Xem chi tiết-Kiểm tra nút <Xóa đề nghị> hiển thị và mở popup xác nhận xóa khi hồ sơ có trạng thái = Bản nháp-- | L83: 1 Marker 1 Checker | M83: Pre: - Tồn tại 1 hồ sơ đề nghị Phát hành LC có trạng thái khác Bản nháp (ví dụ: Chờ duyệt, Đã duyệt, Từ chối, Yêu cầu bổ sung) Step: 1. Đăng nhập hệ thống bằng user có quyền xem chi tiết. 2. Mở màn hình xem chi tiết hồ sơ có trạng thái khác Bản nháp. 3. Quan sát nút <Sao chép> và chọn <Sao chép>. | N83: Nút <Sao chép> hiển thị trên màn hình (do BR quy định nút hiển thị với tất cả các trạng thái trừ trạng thái = Bản nháp). Khi chọn, hệ thống mở Popup xác nhận sao chép đề nghị (theo mục II.1.2.7. Sao chép giao dịch). | O83: High | S83: Not started
A84: 131 | B84: FO | C84: S18 | D84: Xem chi tiết | E84: HF-01/02/03 | F84: Edge case | G84: Xem chi tiết | H84: Kiểm tra nút <Sao chép> không hiển thị khi hồ sơ có trạng thái = Bản nháp | I84: Kiểm tra nút <Sao chép> không hiển thị khi hồ sơ có trạng thái = Bản nháp | K84: Kiểm tra nút <Xóa đề nghị> không hiển thị khi hồ sơ ở trạng thái khác Bản nháp-Thành công-Xem chi tiết-Kiểm tra nút <Xóa đề nghị> không hiển thị khi hồ sơ ở trạng thái khác Bản nháp-- | L84: 1 Marker 1 Checker | M84: Pre: - Tồn tại 1 hồ sơ đề nghị Phát hành LC có trạng thái = Bản nháp Step: 1. Đăng nhập hệ thống bằng user có quyền xem chi tiết. 2. Mở màn hình xem chi tiết hồ sơ có trạng thái = Bản nháp. 3. Quan sát khu vực các nút chức năng trên màn hình. | N84: Nút <Sao chép> không hiển thị trên màn hình (do BR quy định nút không hiển thị khi trạng thái = Bản nháp). | O84: Medium | S84: Not started
A85: 132 | B85: FO | C85: S18 | D85: Xem chi tiết | E85: HF-01/02/03 | F85: Edge case | G85: Xem chi tiết | H85: Kiểm tra nút <Phê duyệt> hiển thị và mở popup phê duyệt khi hồ sơ có trạng thái = Chờ duyệt | I85: Kiểm tra nút <Phê duyệt> hiển thị và mở popup phê duyệt khi hồ sơ có trạng thái = Chờ duyệt | K85: Kiểm tra nút <Hủy giao dịch> hiển thị và mở popup xác nhận hủy đề nghị khi hồ sơ có trạng thái = Yêu cầu bổ sung-Thành công-Xem chi tiết-Kiểm tra nút <Hủy giao dịch> hiển thị và mở popup xác nhận hủy đề nghị khi hồ sơ có trạng thái = Yêu cầu bổ sung-- | L85: 1 Marker 1 Checker | M85: Pre: - Tồn tại 1 hồ sơ đề nghị Phát hành LC có trạng thái = Chờ duyệt Step: 1. Đăng nhập hệ thống bằng user có quyền phê duyệt. 2. Mở màn hình xem chi tiết hồ sơ có trạng thái = Chờ duyệt. 3. Quan sát nút <Phê duyệt> và chọn <Phê duyệt>. | N85: Nút <Phê duyệt> hiển thị trên màn hình (do TT = Chờ duyệt). Khi chọn, hệ thống mở Popup phê duyệt (theo mục II.1.2.8. Phê duyệt). | O85: High | S85: Not started
A86: 133 | B86: FO | C86: S18 | D86: Xem chi tiết | E86: HF-01/02/03 | F86: Edge case | G86: Xem chi tiết | H86: Kiểm tra nút <Phê duyệt> không hiển thị khi hồ sơ ở trạng thái khác Chờ duyệt | I86: Kiểm tra nút <Phê duyệt> không hiển thị khi hồ sơ ở trạng thái khác Chờ duyệt | K86: Kiểm tra nút <Hủy giao dịch> không hiển thị khi hồ sơ ở trạng thái khác Yêu cầu bổ sung-Thành công-Xem chi tiết-Kiểm tra nút <Hủy giao dịch> không hiển thị khi hồ sơ ở trạng thái khác Yêu cầu bổ sung-- | L86: 1 Marker 1 Checker | M86: Pre: - Tồn tại 1 hồ sơ đề nghị Phát hành LC có trạng thái khác Chờ duyệt Step: 1. Đăng nhập hệ thống bằng user có quyền phê duyệt. 2. Mở màn hình xem chi tiết hồ sơ có trạng thái khác Chờ duyệt. 3. Quan sát khu vực các nút chức năng trên màn hình. | N86: Nút <Phê duyệt> không hiển thị trên màn hình (do BR quy định nút chỉ hiển thị với TT = Chờ duyệt). | O86: Medium | S86: Not started
... A88: 135 | B88: FO | C88: S18 | D88: Xem chi tiết | E88: HF-01/02/03 | F88: Edge case | G88: Xem chi tiết | H88: Kiểm tra nút <Từ chối> không hiển thị khi hồ sơ ở trạng thái khác Chờ duyệt | I88: Kiểm tra nút <Từ chối> không hiển thị khi hồ sơ ở trạng thái khác Chờ duyệt | K88: Kiểm tra nút <Sao chép> không hiển thị khi hồ sơ có trạng thái = Bản nháp-Thành công-Xem chi tiết-Kiểm tra nút <Sao chép> không hiển thị khi hồ sơ có trạng thái = Bản nháp-- | L88: 1 Marker | M88: Pre: - Tồn tại 1 hồ sơ đề nghị Phát hành LC có trạng thái khác Chờ duyệt Step: 1. Đăng nhập hệ thống bằng user có quyền phê duyệt. 2. Mở màn hình xem chi tiết hồ sơ có trạng thái khác Chờ duyệt. 3. Quan sát khu vực các nút chức năng trên màn hình. | N88: Nút <Từ chối> không hiển thị trên màn hình (do BR quy định nút chỉ hiển thị với TT = Chờ duyệt). | O88: Medium | S88: Not started
A89: 136 | B89: FO | C89: S18 | D89: Xem chi tiết | E89: HF-01/02/03 | F89: Edge case | G89: Xem chi tiết | H89: Kiểm tra nút <Ký số cá nhân> hiển thị và mở màn hình ký số cá nhân khi hồ sơ có trạng thái = Chờ duyệt cấp tiếp theo | I89: Kiểm tra nút <Ký số cá nhân> hiển thị và mở màn hình ký số cá nhân khi hồ sơ có trạng thái = Chờ duyệt cấp tiếp theo | K89: Kiểm tra nút <Phê duyệt> hiển thị và mở popup phê duyệt khi hồ sơ có trạng thái = Chờ duyệt-Thành công-Xem chi tiết-Kiểm tra nút <Phê duyệt> hiển thị và mở popup phê duyệt khi hồ sơ có trạng thái = Chờ duyệt-- | L89: 1 Marker 1 Checker | M89: Pre: - Tồn tại 1 hồ sơ đề nghị Phát hành LC có trạng thái = Chờ duyệt cấp tiếp theo; user đăng nhập có quyền ký số Step: 1. Đăng nhập hệ thống bằng user có quyền ký số. 2. Mở màn hình xem chi tiết hồ sơ có trạng thái = Chờ duyệt cấp tiếp theo. 3. Quan sát nút <Ký số cá nhân> và chọn <Ký số cá nhân>. | N89: Nút <Ký số cá nhân> hiển thị trên màn hình (do TT = Chờ duyệt cấp tiếp theo). Khi chọn, hệ thống mở màn hình ký số cá nhân (theo mục II.1.2.10. Ký số cá nhân). | O89: High | P89: Cần xác nhận: ký số (USB token/HSM?) | S89: Not started
A90: 137 | B90: FO | C90: S18 | D90: Xem chi tiết | E90: HF-01/02/03 | F90: Edge case | G90: Xem chi tiết | H90: Kiểm tra nút <Ký số cá nhân> không hiển thị khi hồ sơ ở trạng thái khác Chờ duyệt cấp tiếp theo | I90: Kiểm tra nút <Ký số cá nhân> không hiển thị khi hồ sơ ở trạng thái khác Chờ duyệt cấp tiếp theo | K90: Kiểm tra nút <Phê duyệt> không hiển thị khi hồ sơ ở trạng thái khác Chờ duyệt-Thành công-Xem chi tiết-Kiểm tra nút <Phê duyệt> không hiển thị khi hồ sơ ở trạng thái khác Chờ duyệt-- | L90: 1 Marker 1 Checker | M90: Pre: - Tồn tại 1 hồ sơ đề nghị Phát hành LC có trạng thái khác Chờ duyệt cấp tiếp theo Step: 1. Đăng nhập hệ thống bằng user có quyền ký số. 2. Mở màn hình xem chi tiết hồ sơ có trạng thái khác Chờ duyệt cấp tiếp theo. 3. Quan sát khu vực các nút chức năng trên màn hình. | N90: Nút <Ký số cá nhân> không hiển thị trên màn hình (do BR quy định nút chỉ hiển thị với TT = Chờ duyệt cấp tiếp theo). | O90: Medium | P90: Cần xác nhận: ký số (USB token/HSM?) | S90: Not started
A91: 138 | B91: FO | C91: S18 | D91: Xem chi tiết | E91: HF-01/02/03 | F91: Edge case | G91: Xem chi tiết | H91: Trạng thái | I91: Kiểm tra hiển thị trường "Trạng thái" | K91: Kiểm tra nút <Từ chối> hiển thị và mở popup xác nhận từ chối phê duyệt khi hồ sơ có trạng thái = Chờ duyệt-Thành công-Xem chi tiết-Kiểm tra nút <Từ chối> hiển thị và mở popup xác nhận từ chối phê duyệt khi hồ sơ có trạng thái = Chờ duyệt-- | L91: 1 Marker | M91: Step: Truy cập màn hình và quan sát trường "Trạng thái". | N91: Trường "Trạng thái" hiển thị đúng nội dung/nhãn theo mô tả: Hiển thị [Trạng thái] tương ứng | O91: Low | S91: Not started
A92: 139 | B92: FO | C92: S18 | D92: Xem chi tiết | E92: HF-01/02/03 | F92: Edge case | G92: Xem chi tiết | H92: Lịch sử giao dịch | I92: Kiểm tra nhập/hiển thị dữ liệu hợp lệ trường "Lịch sử giao dịch" | K92: Kiểm tra nút <Từ chối> không hiển thị khi hồ sơ ở trạng thái khác Chờ duyệt-Thành công-Xem chi tiết-Kiểm tra nút <Từ chối> không hiển thị khi hồ sơ ở trạng thái khác Chờ duyệt-- | L92: 1 Marker | M92: Step: Nhập/chọn giá trị hợp lệ cho trường "Lịch sử giao dịch" theo mô tả nghiệp vụ rồi thực hiện Lưu/Gửi duyệt. | N92: Hệ thống chấp nhận và xử lý đúng theo mô tả: Khi chọn, mở pop-up xem chi tiết lịch sử của giao dịch | O92: Medium | S92: Not started
A93: 140 | B93: FO | C93: S18 | D93: Xem chi tiết | E93: HF-01/02/03 | F93: Edge case | G93: Xem chi tiết | H93: Mã đề nghị | I93: Kiểm tra hiển thị trường "Mã đề nghị" | K93: Kiểm tra nút <Ký số cá nhân> hiển thị và mở màn hình ký số cá nhân khi hồ sơ có trạng thái = Chờ duyệt cấp tiếp theo-Thành công-Xem chi tiết-Kiểm tra nút <Ký số cá nhân> hiển thị và mở màn hình ký số cá nhân khi hồ sơ có trạng thái = Chờ duyệt cấp tiếp theo-- | L93: 1 Marker | M93: Step: Truy cập màn hình và quan sát trường "Mã đề nghị". | N93: Trường "Mã đề nghị" hiển thị đúng nội dung/nhãn theo mô tả: Hiển thị [Mã đề nghị] tương ứng | O93: Low | P93: Cần xác nhận: ký số (USB token/HSM?) | S93: Not started
A94: 141 | B94: FO | C94: S18 | D94: Xem chi tiết | E94: HF-01/02/03 | F94: Edge case | G94: Xem chi tiết | H94: Ngày đề nghị | I94: Kiểm tra hiển thị trường "Ngày đề nghị" | K94: Kiểm tra nút <Ký số cá nhân> không hiển thị khi hồ sơ ở trạng thái khác Chờ duyệt cấp tiếp theo-Thành công-Xem chi tiết-Kiểm tra nút <Ký số cá nhân> không hiển thị khi hồ sơ ở trạng thái khác Chờ duyệt cấp tiếp theo-- | L94: 1 Marker | M94: Step: Truy cập màn hình và quan sát trường "Ngày đề nghị". | N94: Trường "Ngày đề nghị" hiển thị đúng nội dung/nhãn theo mô tả: Hiển thị [Ngày đề nghị] tương ứng | O94: Low | P94: Cần xác nhận: ký số (USB token/HSM?) | S94: Not started
A95: 142 | B95: FO | C95: S18 | D95: Xem chi tiết | E95: HF-01/02/03 | F95: Edge case | G95: Xem chi tiết | H95: Người tạo | I95: Kiểm tra hiển thị trường "Người tạo" | K95: Trạng thái-Thành công-Xem chi tiết-Kiểm tra hiển thị trường "Trạng thái"-- | L95: 1 Marker | M95: Step: Truy cập màn hình và quan sát trường "Người tạo". | N95: Trường "Người tạo" hiển thị đúng nội dung/nhãn theo mô tả: Hiển thị [Người tạo] tương ứng | O95: Low | S95: Not started
A96: 143 | B96: FO | C96: S18 | D96: Xem chi tiết | E96: HF-01/02/03 | F96: Edge case | G96: Xem chi tiết | H96: Thời gian phê duyệt | I96: Kiểm tra hiển thị trường "Thời gian phê duyệt" | K96: Lịch sử giao dịch-Thành công-Xem chi tiết-Kiểm tra nhập/hiển thị dữ liệu hợp lệ trường "Lịch sử giao dịch"-- | L96: 1 Marker 1 Checker | M96: Step: Truy cập màn hình và quan sát trường "Thời gian phê duyệt". | N96: Trường "Thời gian phê duyệt" hiển thị đúng nội dung/nhãn theo mô tả: Hiển thị [Ngày duyệt] tương ứng của người dùng duyệt gần nhất (nếu có) | O96: Low | S96: Not started
A97: 144 | B97: FO | C97: S18 | D97: Xem chi tiết | E97: HF-01/02/03 | F97: Edge case | G97: Xem chi tiết | H97: Người phê duyệt | I97: Kiểm tra hiển thị trường "Người phê duyệt" | K97: Mã đề nghị-Thành công-Xem chi tiết-Kiểm tra hiển thị trường "Mã đề nghị"-- | L97: 1 Marker 1 Checker | M97: Step: Truy cập màn hình và quan sát trường "Người phê duyệt". | N97: Trường "Người phê duyệt" hiển thị đúng nội dung/nhãn theo mô tả: Hiển thị [Người duyệt] tương ứng của người dùng duyệt gần nhất (nếu có) | O97: Low | S97: Not started
A98: 145 | B98: FO | C98: S18 | D98: Xem chi tiết | E98: HF-01/02/03 | F98: Edge case | G98: Xem chi tiết | H98: Lý do từ chối | I98: Kiểm tra hiển thị trường "Lý do từ chối" | K98: Ngày đề nghị-Thành công-Xem chi tiết-Kiểm tra hiển thị trường "Ngày đề nghị"-- | L98: 1 Marker | M98: Step: Truy cập màn hình và quan sát trường "Lý do từ chối". | N98: Trường "Lý do từ chối" hiển thị đúng nội dung/nhãn theo mô tả: Hiển thị thông tin lý do người dung từ chối | O98: Low | S98: Not started
A99: 146 | B99: FO | C99: S18 | D99: Xem chi tiết | E99: HF-01/02/03 | F99: Edge case | G99: Xem chi tiết | H99: Đóng | I99: Kiểm tra chức năng nút "Đóng" | K99: Người tạo-Thành công-Xem chi tiết-Kiểm tra hiển thị trường "Người tạo"-- | L99: 1 Marker | M99: Step: Tại màn hình, nhấn nút "Đóng" và quan sát kết quả xử lý. | N99: Hệ thống thực hiện đúng chức năng của nút "Đóng" theo mô tả nghiệp vụ: Khi chọn, đóng màn hình hiện tại và không làm gì cả | O99: Medium | S99: Not started
A100: 147 | B100: FO | C100: S18 | D100: Xem chi tiết | E100: HF-01/02/03 | F100: Edge case | G100: Xem chi tiết | H100: Xóa đề nghị | I100: Kiểm tra chức năng nút "Xóa đề nghị" | K100: Thời gian phê duyệt-Thành công-Xem chi tiết-Kiểm tra hiển thị trường "Thời gian phê duyệt"-- | L100: 1 Marker | M100: Step: Tại màn hình, nhấn nút "Xóa đề nghị" và quan sát kết quả xử lý. | N100: Hệ thống thực hiện đúng chức năng của nút "Xóa đề nghị" theo mô tả nghiệp vụ: Khi chọn, mở pop-up xác nhận xóa Hiển thị với TT = Bản nháp Chỉ hiển thị với role maker tạo giao dịch | O100: Medium | S100: Not started
A101: 148 | B101: FO | C101: S18 | D101: Xem chi tiết | E101: HF-01/02/03 | F101: Edge case | G101: Xem chi tiết | H101: Hủy giao dịch | I101: Kiểm tra chức năng nút "Hủy giao dịch" | K101: Người phê duyệt-Thành công-Xem chi tiết-Kiểm tra hiển thị trường "Người phê duyệt"-- | L101: 1 Marker | M101: Step: Tại màn hình, nhấn nút "Hủy giao dịch" và quan sát kết quả xử lý. | N101: Hệ thống thực hiện đúng chức năng của nút "Hủy giao dịch" theo mô tả nghiệp vụ: Khi chọn, mở pop-up xác nhận hủy Hiển thị với TT = Ngân hàng yêu cầu bổ sung, Yêu cầu chỉnh sửa Chỉ hiển thị với role maker tạo giao dịch | O101: Medium | S101: Not started
A102: 149 | B102: FO | C102: S18 | D102: Xem chi tiết | E102: HF-01/02/03 | F102: Edge case | G102: Xem chi tiết | H102: Chỉnh sửa | I102: Kiểm tra chức năng nút "Chỉnh sửa" | K102: Lý do từ chối-Thành công-Xem chi tiết-Kiểm tra hiển thị trường "Lý do từ chối"-- | L102: 1 Marker | M102: Step: Tại màn hình, nhấn nút "Chỉnh sửa" và quan sát kết quả xử lý. | N102: Hệ thống thực hiện đúng chức năng của nút "Chỉnh sửa" theo mô tả nghiệp vụ: Khi chọn, mở màn hình chỉnh sửa Hiển thị với TT = Bản nháp, Ngân hàng yêu cầu bổ sung, Yêu cầu chỉnh sửa Chỉ hiển thị với role maker tạo giao dịch | O102: Medium | S102: Not started
A103: 150 | B103: FO | C103: S18 | D103: Xem chi tiết | E103: HF-01/02/03 | F103: Edge case | G103: Xem chi tiết | H103: Sao chép | I103: Kiểm tra chức năng nút "Sao chép" | K103: Đóng-Thành công-Xem chi tiết-Kiểm tra chức năng nút "Đóng"-- | L103: 1 Marker 1 Checker | M103: Step: Tại màn hình, nhấn nút "Sao chép" và quan sát kết quả xử lý. | N103: Hệ thống thực hiện đúng chức năng của nút "Sao chép" theo mô tả nghiệp vụ: Khi chọn, mở pop-up xác nhận Hiển thị với tất cả TT chỉ trừ TT = Bản nháp Chỉ hiển thị với role maker tạo giao dịch | O103: Medium | S103: Not started
A104: 151 | B104: FO | C104: S18 | D104: Xem chi tiết | E104: HF-01/02/03 | F104: Edge case | G104: Xem chi tiết | H104: Phê duyệt | I104: Kiểm tra chức năng nút "Phê duyệt" | K104: Xóa đề nghị-Thành công-Xem chi tiết-Kiểm tra chức năng nút "Xóa đề nghị"-- | L104: 1 Marker 1 Checker | M104: Step: Tại màn hình, nhấn nút "Phê duyệt" và quan sát kết quả xử lý. | N104: Hệ thống thực hiện đúng chức năng của nút "Phê duyệt" theo mô tả nghiệp vụ: Khi chọn, mở pop-up phê duyệt Hiển thị với TT = Chờ duyệt Chỉ hiển thị với role có quyền phê duyệt giao dịch | O104: Medium | S104: Not started
A105: 152 | B105: FO | C105: S18 | D105: Xem chi tiết | E105: HF-01/02/03 | F105: Edge case | G105: Xem chi tiết | H105: Từ chối | I105: Kiểm tra chức năng nút "Từ chối" | K105: Hủy giao dịch-Thành công-Xem chi tiết-Kiểm tra chức năng nút "Hủy giao dịch"-- | L105: 1 Marker | M105: Step: Tại màn hình, nhấn nút "Từ chối" và quan sát kết quả xử lý. | N105: Hệ thống thực hiện đúng chức năng của nút "Từ chối" theo mô tả nghiệp vụ: Khi chọn, mở pop-up nhập lý do từ chối phê duyệt Hiển thị với TT = Chờ duyệt Chỉ hiển thị với role có quyền phê duyệt giao dịch | O105: Medium | S105: Not started
A106: 153 | B106: FO | C106: S18 | D106: Xem chi tiết | E106: HF-01/02/03 | F106: Edge case | G106: Xem chi tiết | H106: Ký số cá nhân | I106: Kiểm tra chức năng nút "Ký số cá nhân" | K106: Chỉnh sửa-Thành công-Xem chi tiết-Kiểm tra chức năng nút "Chỉnh sửa"-- | L106: 1 Marker 1 Checker | M106: Step: Tại màn hình, nhấn nút "Ký số cá nhân" và quan sát kết quả xử lý. | N106: Hệ thống thực hiện đúng chức năng của nút "Ký số cá nhân" theo mô tả nghiệp vụ: Khi chọn, mở màn hình ký số Hiển thị với TT = Chờ duyệt cấp tiếp theo Chỉ hiển thị với role có quyền ký số cá nhân | O106: Medium | P106: Cần xác nhận: ký số (USB token/HSM?) | S106: Not started
A107: 154 | B107: FO | C107: S02 | D107: Thêm mới – quyền truy cập, điều hướng wizard, tích hợp CIF/GLIMS/Core, hạn mức ngày, Gửi duyệt/Lưu nháp | E107: HF-01/02/03 | F107: Edge case | G107: Thêm mới | H107: Kiểm tra quyền truy cập chức năng "Thêm mới" (FO) | I107: Kiểm tra quyền truy cập chức năng "Thêm mới" (FO) | K107: Sao chép-Thành công-Xem chi tiết-Kiểm tra chức năng nút "Sao chép"-- | L107: 1 Marker | M107: Step: Đăng nhập hệ thống với user được phân quyền (Maker/Checker/Viewer được phân quyền chức năng Phát hành LC), truy cập theo đường dẫn menu tương ứng chức năng "Thêm mới". | N107: User truy cập được chức năng "Thêm mới" theo đúng đường dẫn, hiển thị đúng màn hình UI theo thiết kế SRS. | O107: High | S107: Not started
A108: 155 | B108: FO | C108: S02 | D108: Thêm mới – quyền truy cập, điều hướng wizard, tích hợp CIF/GLIMS/Core, hạn mức ngày, Gửi duyệt/Lưu nháp | E108: HF-01/02/03 | F108: Edge case | G108: Thêm mới | H108: Kiểm tra chặn truy cập chức năng "Thêm mới" (FO) khi không được phân quyền | I108: Kiểm tra chặn truy cập chức năng "Thêm mới" (FO) khi không được phân quyền | K108: Phê duyệt-Thành công-Xem chi tiết-Kiểm tra chức năng nút "Phê duyệt"-- | L108: 1 Marker | M108: Step: Đăng nhập hệ thống với user KHÔNG được phân quyền chức năng "Thêm mới", thử truy cập chức năng. | N108: User không nhìn thấy/không truy cập được chức năng "Thêm mới" trên giao diện. | O108: High | S108: Not started | U108: Phục hồi
A109: 156 | B109: FO | C109: S02 | D109: Thêm mới – quyền truy cập, điều hướng wizard, tích hợp CIF/GLIMS/Core, hạn mức ngày, Gửi duyệt/Lưu nháp | E109: HF-01/02/03 | F109: Edge case | G109: Thêm mới | H109: Verify khi user đăng nhập thành công, hệ thống call API tới BO Admin Portal để lấy đúng thông tin phân quyền: CIF của user thuộc DN đang login, cây phân quyền 4 tầng (TTTM > LCNK > Phát hành LC (PHLC) > Truy vấn hồ sơ (C_PHLC)) và rolename. | I109: Verify khi user đăng nhập thành công, hệ thống call API tới BO Admin Portal để lấy đúng thông tin phân quyền: CIF của user thuộc DN đang login, cây phân quyền 4 tầng (TTTM > LCNK > Phát hành LC (PHLC) > Truy vấn hồ sơ (C_PHLC)) và rolename. | K109: Từ chối-Thành công-Xem chi tiết-Kiểm tra chức năng nút "Từ chối"-- | L109: 1 Marker | M109: Step: 1. Nhập giá trị chỉ gồm toàn ký tự khoảng trắng (hoặc khoảng trắng thừa ở đầu/cuối chuỗi hợp lệ) vào trường "Kỳ giao hàng". 2. Thực hiện lưu nháp/gửi duyệt. | N109: Hệ thống không lưu giá trị toàn khoảng trắng (hoặc khoảng trắng thừa ở đầu/cuối) cho trường "Kỳ giao hàng": tự động loại bỏ khoảng trắng đầu/cuối, hoặc coi như trường rỗng. | O109: Medium | P109: Cần xác nhận: gọi API ngoài | S109: Not started
A110: 157 | B110: FO | C110: S02 | D110: Thêm mới – quyền truy cập, điều hướng wizard, tích hợp CIF/GLIMS/Core, hạn mức ngày, Gửi duyệt/Lưu nháp | E110: HF-01/02/03 | F110: Edge case | G110: Thêm mới | H110: Verify hiển thị trạng thái của các step trong màn hình Thêm mới đúng theo mô tả: step đã hoàn thành hiển thị tick xanh, step hiện tại hiển thị ô màu xanh lá, step chưa tới hiển thị màu xám. | I110: Verify hiển thị trạng thái của các step trong màn hình Thêm mới đúng theo mô tả: step đã hoàn thành hiển thị tick xanh, step hiện tại hiển thị ô màu xanh lá, step chưa tới hiển thị màu xám. | K110: Ký số cá nhân-Thành công-Xem chi tiết-Kiểm tra chức năng nút "Ký số cá nhân"-- | L110: 1 Marker | M110: Pre: - User đang ở màn hình Thêm mới đề nghị phát hành LC (gồm 4 step), đã hoàn thành đầy đủ thông tin bắt buộc của step Step: 1. Mở màn hình Thêm mới (đang ở step 1). 2. Nhập đầy đủ thông tin bắt buộc của step 1, nhấn "Tiếp tục" để sang step 2. 3. Quan sát hiển thị trạng thái (màu sắc/icon) của step 1, step 2, step 3, step 4. | N110: Step 1 (đã hoàn thành) hiển thị tick xanh - Step 2 (đang thực hiện, là step hiện tại) hiển thị ô màu xanh lá - Step 3 và Step 4 (chưa tới) hiển thị màu xám. | O110: Medium | P110: Cần xác nhận: ký số (USB token/HSM?) | S110: Not started
A111: 158 | B111: FO | C111: S02 | D111: Thêm mới – quyền truy cập, điều hướng wizard, tích hợp CIF/GLIMS/Core, hạn mức ngày, Gửi duyệt/Lưu nháp | E111: HF-01/02/03 | F111: Edge case | G111: Thêm mới | H111: Verify user có thể click trực tiếp vào số của step đã hoàn thành (đã tick xanh) để chuyển nhanh tới step đó. | I111: Verify user có thể click trực tiếp vào số của step đã hoàn thành (đã tick xanh) để chuyển nhanh tới step đó. | J111: Ô nhập liệu khi chọn Other | K111: Kiểm tra quyền truy cập chức năng "Thêm mới" (FO)-Thành công-Thêm mới-Kiểm tra quyền truy cập chức năng "Thêm mới" (FO)-- | L111: 1 Marker | M111: Pre: - User đang ở màn hình Thêm mới, đã hoàn thành step 1 và step 2 (đã tick xanh), hiện đang ở step 3. Step: 1. Tại step 3, click vào số của step 1 (đã tick xanh). | N111: Hệ thống chuyển màn hình về step 1, cho phép user xem/sửa lại thông tin của step 1. | O111: Medium | S111: Not started
A112: 159 | B112: FO | C112: S02 | D112: Thêm mới – quyền truy cập, điều hướng wizard, tích hợp CIF/GLIMS/Core, hạn mức ngày, Gửi duyệt/Lưu nháp | E112: HF-01/02/03 | F112: Edge case | G112: Thêm mới | H112: Verify khi step hiện tại chưa hoàn thiện đầy đủ thông tin, hệ thống không cho phép chọn Tiếp tục, Quay lại hoặc chọn vào bất kỳ step nào khác. | I112: Verify khi step hiện tại chưa hoàn thiện đầy đủ thông tin, hệ thống không cho phép chọn Tiếp tục, Quay lại hoặc chọn vào bất kỳ step nào khác. | K112: Kiểm tra chặn truy cập chức năng "Thêm mới" (FO) khi không được phân quyền-Thành công-Thêm mới-Kiểm tra chặn truy cập chức năng "Thêm mới" (FO) khi không được phân quyền-- | L112: 1 Marker | M112: Pre: - User đang ở 1 step (ví dụ step 1) của màn hình Thêm mới, chưa nhập đầy đủ thông tin bắt buộc của step hiện tại. Step: 1. Tại step hiện tại, để trống/chưa hoàn thiện các thông tin bắt buộc. 2. Thử nhấn "Tiếp tục". 3. Thử nhấn "Quay lại". 4. Thử click vào các số step khác (step chưa tick xanh). | N112: Hệ thống không cho phép chọn Tiếp tục, không cho phép chọn Quay lại, và không cho phép chọn vào bất kỳ step nào khác khi step hiện tại chưa hoàn thiện. | O112: High | S112: Not started
...
